{"v":"5.7.1","fr":29.9700012207031,"ip":0,"op":456.000018573261,"w":1080,"h":1080,"nm":"Heat transfer","ddd":0,"assets":[],"layers":[{"ddd":0,"ind":1,"ty":4,"nm":"C Outlines","sr":1,"ks":{"o":{"a":0,"k":100,"ix":11},"r":{"a":0,"k":0,"ix":10},"p":{"a":0,"k":[1034,348,0],"ix":2},"a":{"a":0,"k":[0,0,0],"ix":1},"s":{"a":0,"k":[100,100,100],"ix":6}},"ao":0,"shapes":[{"ty":"gr","it":[{"ind":0,"ty":"sh","ix":1,"ks":{"a":0,"k":{"i":[[1.217,-1.074],[1.69,0],[1.432,1.69],[0,3.982],[-1.454,1.676],[-2.335,0],[-1.182,-0.945],[-0.373,-1.633],[0,0],[1.432,1.346],[3.853,0],[2.707,-2.9],[0,-5.242],[-2.693,-2.857],[-4.182,0],[-2.199,1.669],[-0.945,3.438],[0,0]],"o":[[-1.218,1.074],[-2.292,0],[-1.432,-1.69],[0,-3.752],[1.454,-1.676],[1.69,0],[1.182,0.945],[0,0],[-0.716,-2.521],[-2.406,-2.277],[-4.412,0],[-2.707,2.9],[0,4.956],[2.693,2.857],[3.38,0],[2.198,-1.668],[0,0],[-0.53,2.306]],"v":[[20.732,-6.51],[16.371,-4.898],[10.785,-7.434],[8.637,-15.941],[10.817,-24.084],[16.5,-26.598],[20.808,-25.18],[23.139,-21.313],[29.434,-22.816],[26.211,-28.617],[16.822,-32.033],[6.145,-27.683],[2.084,-15.469],[6.123,-3.749],[16.436,0.537],[24.804,-1.966],[29.52,-9.625],[23.354,-11.58]],"c":true},"ix":2},"nm":"C","mn":"ADBE Vector Shape - Group","hd":false},{"ty":"fl","c":{"a":0,"k":[0,0,0,1],"ix":4},"o":{"a":0,"k":100,"ix":5},"r":1,"bm":0,"nm":"Fill 1","mn":"ADBE Vector Graphic - Fill","hd":false},{"ty":"tr","p":{"a":0,"k":[0,0],"ix":2},"a":{"a":0,"k":[0,0],"ix":1},"s":{"a":0,"k":[100,100],"ix":3},"r":{"a":0,"k":0,"ix":6},"o":{"a":0,"k":100,"ix":7},"sk":{"a":0,"k":0,"ix":4},"sa":{"a":0,"k":0,"ix":5},"nm":"Transform"}],"nm":"C","np":3,"cix":2,"bm":0,"ix":1,"mn":"ADBE Vector Group","hd":false}],"ip":0,"op":456.000018573261,"st":0,"bm":0},{"ddd":0,"ind":2,"ty":3,"nm":"Null 2","sr":1,"ks":{"o":{"a":0,"k":0,"ix":11},"r":{"a":0,"k":0,"ix":10},"p":{"a":0,"k":[540,540,0],"ix":2},"a":{"a":0,"k":[0,0,0],"ix":1},"s":{"a":0,"k":[117,117,100],"ix":6}},"ao":0,"ip":0,"op":456.000018573261,"st":0,"bm":0},{"ddd":0,"ind":9,"ty":4,"nm":"pan","parent":2,"sr":1,"ks":{"o":{"a":0,"k":100,"ix":11},"r":{"a":0,"k":0,"ix":10},"p":{"a":0,"k":[-4,-56,0],"ix":2},"a":{"a":0,"k":[345.5,70.5,0],"ix":1},"s":{"a":0,"k":[55,55,100],"ix":6}},"ao":0,"shapes":[{"ty":"gr","it":[{"ind":0,"ty":"sh","ix":1,"ks":{"a":0,"k":{"i":[[0,0],[0,0],[-45.764,0],[0,0],[0,45.764],[0,0]],"o":[[0,0],[0,45.764],[0,0],[-45.765,0],[0,0],[0,0]],"v":[[-4.603,-69.974],[-4.603,-12.89],[78.26,69.974],[4.604,69.974],[-78.26,-12.89],[-78.26,-69.974]],"c":true},"ix":2},"nm":"Path 1","mn":"ADBE Vector Shape - Group","hd":false},{"ty":"fl","c":{"a":0,"k":[0.247509301877,0.226943311504,0.229109072218,1],"ix":4},"o":{"a":0,"k":100,"ix":5},"r":1,"bm":0,"nm":"Fill 1","mn":"ADBE Vector Graphic - Fill","hd":false},{"ty":"tr","p":{"a":0,"k":[78.51,70.224],"ix":2},"a":{"a":0,"k":[0,0],"ix":1},"s":{"a":0,"k":[100,100],"ix":3},"r":{"a":0,"k":0,"ix":6},"o":{"a":0,"k":100,"ix":7},"sk":{"a":0,"k":0,"ix":4},"sa":{"a":0,"k":0,"ix":5},"nm":"Transform"}],"nm":"Group 1","np":4,"cix":2,"bm":0,"ix":1,"mn":"ADBE Vector Group","hd":false},{"ty":"gr","it":[{"ind":0,"ty":"sh","ix":1,"ks":{"a":0,"k":{"i":[[0,45.764],[0,0],[0,0],[0,0],[45.765,0],[0,0]],"o":[[0,0],[0,0],[0,0],[0,45.764],[0,0],[45.765,0]],"v":[[3.613,-12.89],[3.613,-69.974],[79.251,-69.974],[79.251,-12.89],[-3.613,69.974],[-79.251,69.974]],"c":true},"ix":2},"nm":"Path 1","mn":"ADBE Vector Shape - Group","hd":false},{"ty":"fl","c":{"a":0,"k":[0.403304634842,0.38875615737,0.377710499483,1],"ix":4},"o":{"a":0,"k":100,"ix":5},"r":1,"bm":0,"nm":"Fill 1","mn":"ADBE Vector Graphic - Fill","hd":false},{"ty":"tr","p":{"a":0,"k":[610.54,70.224],"ix":2},"a":{"a":0,"k":[0,0],"ix":1},"s":{"a":0,"k":[100,100],"ix":3},"r":{"a":0,"k":0,"ix":6},"o":{"a":0,"k":100,"ix":7},"sk":{"a":0,"k":0,"ix":4},"sa":{"a":0,"k":0,"ix":5},"nm":"Transform"}],"nm":"Group 2","np":4,"cix":2,"bm":0,"ix":2,"mn":"ADBE Vector Group","hd":false},{"ty":"gr","it":[{"ind":0,"ty":"sh","ix":1,"ks":{"a":0,"k":{"i":[[0,0],[0,0],[45.764,0],[0,0],[0,45.764],[0,0]],"o":[[0,0],[0,45.764],[0,0],[-45.765,0],[0,0],[0,0]],"v":[[344.771,-69.974],[344.771,-12.89],[261.907,69.974],[-261.906,69.974],[-344.771,-12.89],[-344.771,-69.974]],"c":true},"ix":2},"nm":"Path 1","mn":"ADBE Vector Shape - Group","hd":false},{"ty":"fl","c":{"a":0,"k":[0.359622940363,0.335382947735,0.32898086847,1],"ix":4},"o":{"a":0,"k":100,"ix":5},"r":1,"bm":0,"nm":"Fill 1","mn":"ADBE Vector Graphic - Fill","hd":false},{"ty":"tr","p":{"a":0,"k":[345.021,70.224],"ix":2},"a":{"a":0,"k":[0,0],"ix":1},"s":{"a":0,"k":[100,100],"ix":3},"r":{"a":0,"k":0,"ix":6},"o":{"a":0,"k":100,"ix":7},"sk":{"a":0,"k":0,"ix":4},"sa":{"a":0,"k":0,"ix":5},"nm":"Transform"}],"nm":"Group 3","np":4,"cix":2,"bm":0,"ix":3,"mn":"ADBE Vector Group","hd":false}],"ip":0,"op":456.000018573261,"st":0,"bm":0},{"ddd":0,"ind":12,"ty":4,"nm":"oven","parent":2,"sr":1,"ks":{"o":{"a":0,"k":100,"ix":11},"r":{"a":0,"k":0,"ix":10},"p":{"a":0,"k":[-4,216,0],"ix":2},"a":{"a":0,"k":[514,528,0],"ix":1},"s":{"a":0,"k":[44,44,100],"ix":6}},"ao":0,"shapes":[{"ty":"gr","it":[{"ind":0,"ty":"sh","ix":1,"ks":{"a":0,"k":{"i":[[0,0],[0,0],[0,0],[0,0]],"o":[[0,0],[0,0],[0,0],[0,0]],"v":[[-192.612,14.764],[-178.799,-14.764],[171.864,-14.764],[192.612,14.764]],"c":true},"ix":2},"nm":"Path 1","mn":"ADBE Vector Shape - Group","hd":false},{"ty":"fl","c":{"a":0,"k":[0.541735361137,0.550035125134,0.54891279632,1],"ix":4},"o":{"a":0,"k":100,"ix":5},"r":1,"bm":0,"nm":"Fill 1","mn":"ADBE Vector Graphic - Fill","hd":false},{"ty":"tr","p":{"a":0,"k":[517.275,7.433],"ix":2},"a":{"a":0,"k":[0,0],"ix":1},"s":{"a":0,"k":[100,100],"ix":3},"r":{"a":0,"k":0,"ix":6},"o":{"a":0,"k":100,"ix":7},"sk":{"a":0,"k":0,"ix":4},"sa":{"a":0,"k":0,"ix":5},"nm":"Transform"}],"nm":"Group 1","np":4,"cix":2,"bm":0,"ix":1,"mn":"ADBE Vector Group","hd":false},{"ty":"gr","it":[{"ind":0,"ty":"sh","ix":1,"ks":{"a":0,"k":{"i":[[0,0],[0,0],[0,0],[3.691,0],[0,0],[0,-3.692]],"o":[[0,0],[0,0],[0,-3.692],[0,0],[-3.693,0],[0,0]],"v":[[-513.555,33.424],[513.555,33.424],[513.555,-26.739],[506.87,-33.424],[-506.869,-33.424],[-513.555,-26.739]],"c":true},"ix":2},"nm":"Path 1","mn":"ADBE Vector Shape - Group","hd":false},{"ty":"fl","c":{"a":0,"k":[0.764312744141,0.80498046875,0.798611569872,1],"ix":4},"o":{"a":0,"k":100,"ix":5},"r":1,"bm":0,"nm":"Fill 1","mn":"ADBE Vector Graphic - Fill","hd":false},{"ty":"tr","p":{"a":0,"k":[513.805,61.988],"ix":2},"a":{"a":0,"k":[0,0],"ix":1},"s":{"a":0,"k":[100,100],"ix":3},"r":{"a":0,"k":0,"ix":6},"o":{"a":0,"k":100,"ix":7},"sk":{"a":0,"k":0,"ix":4},"sa":{"a":0,"k":0,"ix":5},"nm":"Transform"}],"nm":"Group 2","np":4,"cix":2,"bm":0,"ix":2,"mn":"ADBE Vector Group","hd":false},{"ty":"gr","it":[{"ind":0,"ty":"sh","ix":1,"ks":{"a":0,"k":{"i":[[0,0],[0,0],[0,5.826],[0,0],[0,0]],"o":[[0,0],[-4.185,-3.342],[0,0],[0,0],[0,0]],"v":[[233.109,-230.674],[-226.263,230.674],[-233.11,216.349],[-233.11,100.99],[97.199,-230.674]],"c":true},"ix":2},"nm":"Path 1","mn":"ADBE Vector Shape - Group","hd":false},{"ty":"fl","c":{"a":0,"k":[0.71202655867,0.865476122089,0.832852172852,1],"ix":4},"o":{"a":0,"k":100,"ix":5},"r":1,"bm":0,"nm":"Fill 1","mn":"ADBE Vector Graphic - Fill","hd":false},{"ty":"tr","p":{"a":0,"k":[417.655,659.945],"ix":2},"a":{"a":0,"k":[0,0],"ix":1},"s":{"a":0,"k":[100,100],"ix":3},"r":{"a":0,"k":0,"ix":6},"o":{"a":0,"k":100,"ix":7},"sk":{"a":0,"k":0,"ix":4},"sa":{"a":0,"k":0,"ix":5},"nm":"Transform"}],"nm":"Group 3","np":4,"cix":2,"bm":0,"ix":3,"mn":"ADBE Vector Group","hd":false},{"ty":"gr","it":[{"ind":0,"ty":"sh","ix":1,"ks":{"a":0,"k":{"i":[[0,0],[0,0],[0,0],[0,0]],"o":[[0,0],[0,0],[0,0],[0,0]],"v":[[214.897,-215.777],[214.897,19.434],[19.45,215.777],[-214.897,215.777]],"c":true},"ix":2},"nm":"Path 1","mn":"ADBE Vector Shape - Group","hd":false},{"ty":"fl","c":{"a":0,"k":[0.71202655867,0.865476122089,0.832852172852,1],"ix":4},"o":{"a":0,"k":100,"ix":5},"r":1,"bm":0,"nm":"Fill 1","mn":"ADBE Vector Graphic - Fill","hd":false},{"ty":"tr","p":{"a":0,"k":[625.037,679.045],"ix":2},"a":{"a":0,"k":[0,0],"ix":1},"s":{"a":0,"k":[100,100],"ix":3},"r":{"a":0,"k":0,"ix":6},"o":{"a":0,"k":100,"ix":7},"sk":{"a":0,"k":0,"ix":4},"sa":{"a":0,"k":0,"ix":5},"nm":"Transform"}],"nm":"Group 4","np":4,"cix":2,"bm":0,"ix":4,"mn":"ADBE Vector Group","hd":false},{"ty":"gr","it":[{"ind":0,"ty":"sh","ix":1,"ks":{"a":0,"k":{"i":[[0,0],[0,0],[0,0],[0,0]],"o":[[0,0],[0,0],[0,0],[0,0]],"v":[[-253.621,4.775],[253.621,4.775],[253.621,-4.775],[-253.621,-4.775]],"c":true},"ix":2},"nm":"Path 1","mn":"ADBE Vector Shape - Group","hd":false},{"ty":"fl","c":{"a":0,"k":[0.771215401444,0.766354609471,0.766106758866,1],"ix":4},"o":{"a":0,"k":100,"ix":5},"r":1,"bm":0,"nm":"Fill 1","mn":"ADBE Vector Graphic - Fill","hd":false},{"ty":"tr","p":{"a":0,"k":[499.32,687.497],"ix":2},"a":{"a":0,"k":[0,0],"ix":1},"s":{"a":0,"k":[100,100],"ix":3},"r":{"a":0,"k":0,"ix":6},"o":{"a":0,"k":100,"ix":7},"sk":{"a":0,"k":0,"ix":4},"sa":{"a":0,"k":0,"ix":5},"nm":"Transform"}],"nm":"Group 5","np":4,"cix":2,"bm":0,"ix":5,"mn":"ADBE Vector Group","hd":false},{"ty":"gr","it":[{"ind":0,"ty":"sh","ix":1,"ks":{"a":0,"k":{"i":[[0,0],[0,0],[0,0],[0,0]],"o":[[0,0],[0,0],[0,0],[0,0]],"v":[[-253.621,4.775],[253.621,4.775],[253.621,-4.775],[-253.621,-4.775]],"c":true},"ix":2},"nm":"Path 1","mn":"ADBE Vector Shape - Group","hd":false},{"ty":"fl","c":{"a":0,"k":[0.771215401444,0.766354609471,0.766106758866,1],"ix":4},"o":{"a":0,"k":100,"ix":5},"r":1,"bm":0,"nm":"Fill 1","mn":"ADBE Vector Graphic - Fill","hd":false},{"ty":"tr","p":{"a":0,"k":[499.32,614.282],"ix":2},"a":{"a":0,"k":[0,0],"ix":1},"s":{"a":0,"k":[100,100],"ix":3},"r":{"a":0,"k":0,"ix":6},"o":{"a":0,"k":100,"ix":7},"sk":{"a":0,"k":0,"ix":4},"sa":{"a":0,"k":0,"ix":5},"nm":"Transform"}],"nm":"Group 6","np":4,"cix":2,"bm":0,"ix":6,"mn":"ADBE Vector Group","hd":false},{"ty":"gr","it":[{"ind":0,"ty":"sh","ix":1,"ks":{"a":0,"k":{"i":[[0,0],[0,0],[0,0],[0,0]],"o":[[0,0],[0,0],[0,0],[0,0]],"v":[[-385.188,3.979],[385.188,3.979],[385.188,-3.979],[-385.188,-3.979]],"c":true},"ix":2},"nm":"Path 1","mn":"ADBE Vector Shape - Group","hd":false},{"ty":"fl","c":{"a":0,"k":[0.054547911999,0.049028344248,0.062417669857,1],"ix":4},"o":{"a":0,"k":100,"ix":5},"r":1,"bm":0,"nm":"Fill 1","mn":"ADBE Vector Graphic - Fill","hd":false},{"ty":"tr","p":{"a":0,"k":[512.001,314.261],"ix":2},"a":{"a":0,"k":[0,0],"ix":1},"s":{"a":0,"k":[100,100],"ix":3},"r":{"a":0,"k":0,"ix":6},"o":{"a":0,"k":100,"ix":7},"sk":{"a":0,"k":0,"ix":4},"sa":{"a":0,"k":0,"ix":5},"nm":"Transform"}],"nm":"Group 7","np":4,"cix":2,"bm":0,"ix":7,"mn":"ADBE Vector Group","hd":false},{"ty":"gr","it":[{"ind":0,"ty":"sh","ix":1,"ks":{"a":0,"k":{"i":[[0,0],[0,0],[0,0],[0,0]],"o":[[0,0],[0,0],[0,0],[0,0]],"v":[[-241.931,4.368],[241.931,4.368],[241.931,-4.368],[-241.931,-4.368]],"c":true},"ix":2},"nm":"Path 1","mn":"ADBE Vector Shape - Group","hd":false},{"ty":"fl","c":{"a":0,"k":[0.530204384,0.52011533251,0.493861568675,1],"ix":4},"o":{"a":0,"k":100,"ix":5},"r":1,"bm":0,"nm":"Fill 1","mn":"ADBE Vector Graphic - Fill","hd":false},{"ty":"tr","p":{"a":0,"k":[513.14,375.132],"ix":2},"a":{"a":0,"k":[0,0],"ix":1},"s":{"a":0,"k":[100,100],"ix":3},"r":{"a":0,"k":0,"ix":6},"o":{"a":0,"k":100,"ix":7},"sk":{"a":0,"k":0,"ix":4},"sa":{"a":0,"k":0,"ix":5},"nm":"Transform"}],"nm":"Group 8","np":4,"cix":2,"bm":0,"ix":8,"mn":"ADBE Vector Group","hd":false},{"ty":"gr","it":[{"ind":0,"ty":"sh","ix":1,"ks":{"a":0,"k":{"i":[[0,0],[0,0],[0,0],[0,0]],"o":[[0,0],[0,0],[0,0],[0,0]],"v":[[-241.931,2.992],[241.931,2.992],[241.931,-2.992],[-241.931,-2.992]],"c":true},"ix":2},"nm":"Path 1","mn":"ADBE Vector Shape - Group","hd":false},{"ty":"fl","c":{"a":0,"k":[0.67915428012,0.66974810432,0.635588223326,1],"ix":4},"o":{"a":0,"k":100,"ix":5},"r":1,"bm":0,"nm":"Fill 1","mn":"ADBE Vector Graphic - Fill","hd":false},{"ty":"tr","p":{"a":0,"k":[513.14,350.263],"ix":2},"a":{"a":0,"k":[0,0],"ix":1},"s":{"a":0,"k":[100,100],"ix":3},"r":{"a":0,"k":0,"ix":6},"o":{"a":0,"k":100,"ix":7},"sk":{"a":0,"k":0,"ix":4},"sa":{"a":0,"k":0,"ix":5},"nm":"Transform"}],"nm":"Group 9","np":4,"cix":2,"bm":0,"ix":9,"mn":"ADBE Vector Group","hd":false},{"ty":"gr","it":[{"ind":0,"ty":"sh","ix":1,"ks":{"a":0,"k":{"i":[[0,0],[0,0],[0,0],[0,0]],"o":[[0,0],[0,0],[0,0],[0,0]],"v":[[-241.931,16.115],[241.931,16.115],[241.931,-16.115],[-241.931,-16.115]],"c":true},"ix":2},"nm":"Path 1","mn":"ADBE Vector Shape - Group","hd":false},{"ty":"fl","c":{"a":0,"k":[0.597668397193,0.583428835401,0.554025926777,1],"ix":4},"o":{"a":0,"k":100,"ix":5},"r":1,"bm":0,"nm":"Fill 1","mn":"ADBE Vector Graphic - Fill","hd":false},{"ty":"tr","p":{"a":0,"k":[513.14,363.385],"ix":2},"a":{"a":0,"k":[0,0],"ix":1},"s":{"a":0,"k":[100,100],"ix":3},"r":{"a":0,"k":0,"ix":6},"o":{"a":0,"k":100,"ix":7},"sk":{"a":0,"k":0,"ix":4},"sa":{"a":0,"k":0,"ix":5},"nm":"Transform"}],"nm":"Group 10","np":4,"cix":2,"bm":0,"ix":10,"mn":"ADBE Vector Group","hd":false},{"ty":"gr","it":[{"ind":0,"ty":"sh","ix":1,"ks":{"a":0,"k":{"i":[[0,0],[0,0],[0,0],[0,0],[0,0],[0,0],[0,0],[0,0]],"o":[[0,0],[0,0],[0,0],[0,0],[0,0],[0,0],[0,0],[0,0]],"v":[[21.776,0],[3.88,3.177],[0,21.865],[-3.881,3.177],[-21.776,0],[-3.881,-3.177],[0,-21.865],[3.88,-3.177]],"c":true},"ix":2},"nm":"Path 1","mn":"ADBE Vector Shape - Group","hd":false},{"ty":"fl","c":{"a":0,"k":[0.099417705162,0.088149725222,0.10322338179,1],"ix":4},"o":{"a":0,"k":100,"ix":5},"r":1,"bm":0,"nm":"Fill 1","mn":"ADBE Vector Graphic - Fill","hd":false},{"ty":"tr","p":{"a":0,"k":[309.747,260.109],"ix":2},"a":{"a":0,"k":[0,0],"ix":1},"s":{"a":0,"k":[100,100],"ix":3},"r":{"a":0,"k":0,"ix":6},"o":{"a":0,"k":100,"ix":7},"sk":{"a":0,"k":0,"ix":4},"sa":{"a":0,"k":0,"ix":5},"nm":"Transform"}],"nm":"Group 11","np":4,"cix":2,"bm":0,"ix":11,"mn":"ADBE Vector Group","hd":false},{"ty":"gr","it":[{"ind":0,"ty":"sh","ix":1,"ks":{"a":0,"k":{"i":[[0,0],[-10.712,0],[-4.64,-8.938],[0,0],[11.152,0],[4.701,-9.377]],"o":[[4.639,-8.938],[10.711,0],[0,0],[-4.7,-9.377],[-11.153,0],[0,0]],"v":[[-24.561,7.944],[0,-7.175],[24.562,7.944],[25.43,7.944],[0,-7.944],[-25.43,7.944]],"c":true},"ix":2},"nm":"Path 1","mn":"ADBE Vector Shape - Group","hd":false},{"ty":"fl","c":{"a":0,"k":[0.078444791308,0.073583161597,0.087722284654,1],"ix":4},"o":{"a":0,"k":100,"ix":5},"r":1,"bm":0,"nm":"Fill 1","mn":"ADBE Vector Graphic - Fill","hd":false},{"ty":"tr","p":{"a":0,"k":[309.747,235.822],"ix":2},"a":{"a":0,"k":[0,0],"ix":1},"s":{"a":0,"k":[100,100],"ix":3},"r":{"a":0,"k":0,"ix":6},"o":{"a":0,"k":100,"ix":7},"sk":{"a":0,"k":0,"ix":4},"sa":{"a":0,"k":0,"ix":5},"nm":"Transform"}],"nm":"Group 12","np":4,"cix":2,"bm":0,"ix":12,"mn":"ADBE Vector Group","hd":false},{"ty":"gr","it":[{"ind":0,"ty":"sh","ix":1,"ks":{"a":0,"k":{"i":[[0,-12.966],[12.913,0],[0,12.966],[-12.912,0]],"o":[[0,12.966],[-12.912,0],[0,-12.966],[12.913,0]],"v":[[23.381,0],[0,23.477],[-23.381,0],[0,-23.477]],"c":true},"ix":2},"nm":"Path 1","mn":"ADBE Vector Shape - Group","hd":false},{"ty":"fl","c":{"a":0,"k":[0.078444791308,0.073583161597,0.087722284654,1],"ix":4},"o":{"a":0,"k":100,"ix":5},"r":1,"bm":0,"nm":"Fill 1","mn":"ADBE Vector Graphic - Fill","hd":false},{"ty":"tr","p":{"a":0,"k":[309.747,260.109],"ix":2},"a":{"a":0,"k":[0,0],"ix":1},"s":{"a":0,"k":[100,100],"ix":3},"r":{"a":0,"k":0,"ix":6},"o":{"a":0,"k":100,"ix":7},"sk":{"a":0,"k":0,"ix":4},"sa":{"a":0,"k":0,"ix":5},"nm":"Transform"}],"nm":"Group 13","np":4,"cix":2,"bm":0,"ix":13,"mn":"ADBE Vector Group","hd":false},{"ty":"gr","it":[{"ind":0,"ty":"sh","ix":1,"ks":{"a":0,"k":{"i":[[0,0],[0,0],[0,0],[0,0],[0,0],[0,0],[0,0],[0,0]],"o":[[0,0],[0,0],[0,0],[0,0],[0,0],[0,0],[0,0],[0,0]],"v":[[21.776,0],[3.881,3.177],[0.001,21.865],[-3.88,3.177],[-21.776,0],[-3.88,-3.177],[0.001,-21.865],[3.881,-3.177]],"c":true},"ix":2},"nm":"Path 1","mn":"ADBE Vector Shape - Group","hd":false},{"ty":"fl","c":{"a":0,"k":[0.099417705162,0.088149725222,0.10322338179,1],"ix":4},"o":{"a":0,"k":100,"ix":5},"r":1,"bm":0,"nm":"Fill 1","mn":"ADBE Vector Graphic - Fill","hd":false},{"ty":"tr","p":{"a":0,"k":[714.748,260.109],"ix":2},"a":{"a":0,"k":[0,0],"ix":1},"s":{"a":0,"k":[100,100],"ix":3},"r":{"a":0,"k":0,"ix":6},"o":{"a":0,"k":100,"ix":7},"sk":{"a":0,"k":0,"ix":4},"sa":{"a":0,"k":0,"ix":5},"nm":"Transform"}],"nm":"Group 14","np":4,"cix":2,"bm":0,"ix":14,"mn":"ADBE Vector Group","hd":false},{"ty":"gr","it":[{"ind":0,"ty":"sh","ix":1,"ks":{"a":0,"k":{"i":[[0,0],[-10.712,0],[-4.639,-8.938],[0,0],[11.152,0],[4.701,-9.377]],"o":[[4.639,-8.938],[10.712,0],[0,0],[-4.701,-9.377],[-11.153,0],[0,0]],"v":[[-24.562,7.944],[0,-7.175],[24.562,7.944],[25.43,7.944],[0,-7.944],[-25.43,7.944]],"c":true},"ix":2},"nm":"Path 1","mn":"ADBE Vector Shape - Group","hd":false},{"ty":"fl","c":{"a":0,"k":[0.078444791308,0.073583161597,0.087722284654,1],"ix":4},"o":{"a":0,"k":100,"ix":5},"r":1,"bm":0,"nm":"Fill 1","mn":"ADBE Vector Graphic - Fill","hd":false},{"ty":"tr","p":{"a":0,"k":[714.749,235.822],"ix":2},"a":{"a":0,"k":[0,0],"ix":1},"s":{"a":0,"k":[100,100],"ix":3},"r":{"a":0,"k":0,"ix":6},"o":{"a":0,"k":100,"ix":7},"sk":{"a":0,"k":0,"ix":4},"sa":{"a":0,"k":0,"ix":5},"nm":"Transform"}],"nm":"Group 15","np":4,"cix":2,"bm":0,"ix":15,"mn":"ADBE Vector Group","hd":false},{"ty":"gr","it":[{"ind":0,"ty":"sh","ix":1,"ks":{"a":0,"k":{"i":[[0,-12.966],[12.913,0],[0,12.966],[-12.913,0]],"o":[[0,12.966],[-12.913,0],[0,-12.966],[12.913,0]],"v":[[23.381,0],[0,23.477],[-23.381,0],[0,-23.477]],"c":true},"ix":2},"nm":"Path 1","mn":"ADBE Vector Shape - Group","hd":false},{"ty":"fl","c":{"a":0,"k":[0.078444791308,0.073583161597,0.087722284654,1],"ix":4},"o":{"a":0,"k":100,"ix":5},"r":1,"bm":0,"nm":"Fill 1","mn":"ADBE Vector Graphic - Fill","hd":false},{"ty":"tr","p":{"a":0,"k":[714.749,260.109],"ix":2},"a":{"a":0,"k":[0,0],"ix":1},"s":{"a":0,"k":[100,100],"ix":3},"r":{"a":0,"k":0,"ix":6},"o":{"a":0,"k":100,"ix":7},"sk":{"a":0,"k":0,"ix":4},"sa":{"a":0,"k":0,"ix":5},"nm":"Transform"}],"nm":"Group 16","np":4,"cix":2,"bm":0,"ix":16,"mn":"ADBE Vector Group","hd":false},{"ty":"gr","it":[{"ind":0,"ty":"sh","ix":1,"ks":{"a":0,"k":{"i":[[0,0],[0,0],[0,0],[0,0]],"o":[[0,0],[0,0],[0,0],[0,0]],"v":[[51.318,15.12],[-51.318,15.12],[-51.318,-15.12],[51.318,-15.12]],"c":true},"ix":2},"nm":"Path 1","mn":"ADBE Vector Shape - Group","hd":false},{"ty":"fl","c":{"a":0,"k":[0.159225912655,0.1436839085,0.16593171662,1],"ix":4},"o":{"a":0,"k":100,"ix":5},"r":1,"bm":0,"nm":"Fill 1","mn":"ADBE Vector Graphic - Fill","hd":false},{"ty":"tr","p":{"a":0,"k":[515.517,222.726],"ix":2},"a":{"a":0,"k":[0,0],"ix":1},"s":{"a":0,"k":[100,100],"ix":3},"r":{"a":0,"k":0,"ix":6},"o":{"a":0,"k":100,"ix":7},"sk":{"a":0,"k":0,"ix":4},"sa":{"a":0,"k":0,"ix":5},"nm":"Transform"}],"nm":"Group 17","np":4,"cix":2,"bm":0,"ix":17,"mn":"ADBE Vector Group","hd":false},{"ty":"gr","it":[{"ind":0,"ty":"sh","ix":1,"ks":{"a":0,"k":{"i":[[0,0],[0,0],[0,0],[0,0]],"o":[[0,0],[0,0],[0,0],[0,0]],"v":[[95.306,9.748],[-95.306,9.748],[-95.306,-9.748],[95.306,-9.748]],"c":true},"ix":2},"nm":"Path 1","mn":"ADBE Vector Shape - Group","hd":false},{"ty":"fl","c":{"a":0,"k":[0.094917618995,0.08518892924,0.094413405774,1],"ix":4},"o":{"a":0,"k":100,"ix":5},"r":1,"bm":0,"nm":"Fill 1","mn":"ADBE Vector Graphic - Fill","hd":false},{"ty":"tr","p":{"a":0,"k":[515.518,265.103],"ix":2},"a":{"a":0,"k":[0,0],"ix":1},"s":{"a":0,"k":[100,100],"ix":3},"r":{"a":0,"k":0,"ix":6},"o":{"a":0,"k":100,"ix":7},"sk":{"a":0,"k":0,"ix":4},"sa":{"a":0,"k":0,"ix":5},"nm":"Transform"}],"nm":"Group 18","np":4,"cix":2,"bm":0,"ix":18,"mn":"ADBE Vector Group","hd":false},{"ty":"gr","it":[{"ind":0,"ty":"sh","ix":1,"ks":{"a":0,"k":{"i":[[0,0],[0,0],[0,0],[0,0]],"o":[[0,0],[0,0],[0,0],[0,0]],"v":[[98.081,41.781],[-98.081,41.781],[-98.081,-41.781],[98.081,-41.781]],"c":true},"ix":2},"nm":"Path 1","mn":"ADBE Vector Shape - Group","hd":false},{"ty":"fl","c":{"a":0,"k":[0.078444791308,0.073583161597,0.087722284654,1],"ix":4},"o":{"a":0,"k":100,"ix":5},"r":1,"bm":0,"nm":"Fill 1","mn":"ADBE Vector Graphic - Fill","hd":false},{"ty":"tr","p":{"a":0,"k":[515.517,235.458],"ix":2},"a":{"a":0,"k":[0,0],"ix":1},"s":{"a":0,"k":[100,100],"ix":3},"r":{"a":0,"k":0,"ix":6},"o":{"a":0,"k":100,"ix":7},"sk":{"a":0,"k":0,"ix":4},"sa":{"a":0,"k":0,"ix":5},"nm":"Transform"}],"nm":"Group 19","np":4,"cix":2,"bm":0,"ix":19,"mn":"ADBE Vector Group","hd":false},{"ty":"gr","it":[{"ind":0,"ty":"sh","ix":1,"ks":{"a":0,"k":{"i":[[0,-10.219],[0,0],[10.177,0],[0,0],[3.139,2.579],[0,5.825],[0,0],[-10.176,0],[0,0]],"o":[[0,0],[0,10.218],[0,0],[-4.375,0],[-4.184,-3.342],[0,0],[0,-10.219],[0,0],[10.177,0]],"v":[[327.695,-214.248],[327.695,214.249],[309.243,232.775],[-309.243,232.775],[-320.847,228.573],[-327.695,214.249],[-327.695,-214.248],[-309.243,-232.775],[309.243,-232.775]],"c":true},"ix":2},"nm":"Path 1","mn":"ADBE Vector Shape - Group","hd":false},{"ty":"fl","c":{"a":0,"k":[0.541735361137,0.550035125134,0.54891279632,1],"ix":4},"o":{"a":0,"k":100,"ix":5},"r":1,"bm":0,"nm":"Fill 1","mn":"ADBE Vector Graphic - Fill","hd":false},{"ty":"tr","p":{"a":0,"k":[512.239,662.046],"ix":2},"a":{"a":0,"k":[0,0],"ix":1},"s":{"a":0,"k":[100,100],"ix":3},"r":{"a":0,"k":0,"ix":6},"o":{"a":0,"k":100,"ix":7},"sk":{"a":0,"k":0,"ix":4},"sa":{"a":0,"k":0,"ix":5},"nm":"Transform"}],"nm":"Group 20","np":4,"cix":2,"bm":0,"ix":20,"mn":"ADBE Vector Group","hd":false},{"ty":"gr","it":[{"ind":0,"ty":"sh","ix":1,"ks":{"a":0,"k":{"i":[[3.119,0],[0,0],[0,3.12],[0,0],[-3.119,0],[0,0],[0,-3.119],[0,0]],"o":[[0,0],[-3.119,0],[0,0],[0,-3.119],[0,0],[3.119,0],[0,0],[0,3.12]],"v":[[379.786,419.112],[-379.786,419.112],[-385.433,413.464],[-385.433,-413.463],[-379.786,-419.112],[379.786,-419.112],[385.433,-413.463],[385.433,413.464]],"c":true},"ix":2},"nm":"Path 1","mn":"ADBE Vector Shape - Group","hd":false},{"ty":"fl","c":{"a":0,"k":[0.929121129653,0.935710772346,0.902293126723,1],"ix":4},"o":{"a":0,"k":100,"ix":5},"r":1,"bm":0,"nm":"Fill 1","mn":"ADBE Vector Graphic - Fill","hd":false},{"ty":"tr","p":{"a":0,"k":[512.248,559.652],"ix":2},"a":{"a":0,"k":[0,0],"ix":1},"s":{"a":0,"k":[100,100],"ix":3},"r":{"a":0,"k":0,"ix":6},"o":{"a":0,"k":100,"ix":7},"sk":{"a":0,"k":0,"ix":4},"sa":{"a":0,"k":0,"ix":5},"nm":"Transform"}],"nm":"Group 21","np":4,"cix":2,"bm":0,"ix":21,"mn":"ADBE Vector Group","hd":false},{"ty":"gr","it":[{"ind":0,"ty":"sh","ix":1,"ks":{"a":0,"k":{"i":[[0.292,0],[0,0],[0,-0.292],[0,0],[-0.292,0],[0,0],[0,0.292],[0,0]],"o":[[0,0],[-0.292,0],[0,0],[0,0.292],[0,0],[0.292,0],[0,0],[0,-0.292]],"v":[[383.074,-5.056],[-383.072,-5.056],[-383.602,-4.527],[-383.602,4.527],[-383.072,5.056],[383.074,5.056],[383.602,4.527],[383.602,-4.527]],"c":true},"ix":2},"nm":"Path 1","mn":"ADBE Vector Shape - Group","hd":false},{"ty":"fl","c":{"a":0,"k":[0.929121129653,0.935710772346,0.902293126723,1],"ix":4},"o":{"a":0,"k":100,"ix":5},"r":1,"bm":0,"nm":"Fill 1","mn":"ADBE Vector Graphic - Fill","hd":false},{"ty":"tr","p":{"a":0,"k":[512.248,24.07],"ix":2},"a":{"a":0,"k":[0,0],"ix":1},"s":{"a":0,"k":[100,100],"ix":3},"r":{"a":0,"k":0,"ix":6},"o":{"a":0,"k":100,"ix":7},"sk":{"a":0,"k":0,"ix":4},"sa":{"a":0,"k":0,"ix":5},"nm":"Transform"}],"nm":"Group 22","np":4,"cix":2,"bm":0,"ix":22,"mn":"ADBE Vector Group","hd":false},{"ty":"gr","it":[{"ind":0,"ty":"sh","ix":1,"ks":{"a":0,"k":{"i":[[0,0],[0,0],[0,0],[0,0]],"o":[[0,0],[0,0],[0,0],[0,0]],"v":[[-491.718,8.754],[491.718,8.754],[491.718,-8.754],[-491.718,-8.754]],"c":true},"ix":2},"nm":"Path 1","mn":"ADBE Vector Shape - Group","hd":false},{"ty":"fl","c":{"a":0,"k":[0.625993556602,0.60275627585,0.57785578709,1],"ix":4},"o":{"a":0,"k":100,"ix":5},"r":1,"bm":0,"nm":"Fill 1","mn":"ADBE Vector Graphic - Fill","hd":false},{"ty":"tr","p":{"a":0,"k":[513.804,102.783],"ix":2},"a":{"a":0,"k":[0,0],"ix":1},"s":{"a":0,"k":[100,100],"ix":3},"r":{"a":0,"k":0,"ix":6},"o":{"a":0,"k":100,"ix":7},"sk":{"a":0,"k":0,"ix":4},"sa":{"a":0,"k":0,"ix":5},"nm":"Transform"}],"nm":"Group 23","np":2,"cix":2,"bm":0,"ix":23,"mn":"ADBE Vector Group","hd":false},{"ty":"gr","it":[{"ind":0,"ty":"sh","ix":1,"ks":{"a":0,"k":{"i":[[0,0],[0,0],[0,0],[0,0]],"o":[[0,0],[0,0],[0,0],[0,0]],"v":[[439.948,479.875],[-439.948,479.875],[-439.948,-479.875],[439.948,-479.875]],"c":true},"ix":2},"nm":"Path 1","mn":"ADBE Vector Shape - Group","hd":false},{"ty":"fl","c":{"a":0,"k":[0.032637405396,0.078659035178,0.235110294118,1],"ix":4},"o":{"a":0,"k":100,"ix":5},"r":1,"bm":0,"nm":"Fill 1","mn":"ADBE Vector Graphic - Fill","hd":false},{"ty":"tr","p":{"a":0,"k":[509.15,575.287],"ix":2},"a":{"a":0,"k":[0,0],"ix":1},"s":{"a":0,"k":[100,100],"ix":3},"r":{"a":0,"k":0,"ix":6},"o":{"a":0,"k":100,"ix":7},"sk":{"a":0,"k":0,"ix":4},"sa":{"a":0,"k":0,"ix":5},"nm":"Transform"}],"nm":"Group 24","np":2,"cix":2,"bm":0,"ix":24,"mn":"ADBE Vector Group","hd":false}],"ip":0,"op":456.000018573261,"st":0,"bm":0},{"ddd":0,"ind":13,"ty":4,"nm":"Layer 2/termometer Outlines","sr":1,"ks":{"o":{"a":0,"k":100,"ix":11},"r":{"a":0,"k":0,"ix":10},"p":{"a":0,"k":[977,442,0],"ix":2},"a":{"a":0,"k":[610,610,0],"ix":1},"s":{"a":0,"k":[100,100,100],"ix":6}},"ao":0,"shapes":[{"ty":"gr","it":[{"ind":0,"ty":"sh","ix":1,"ks":{"a":0,"k":{"i":[[0,0],[0,0]],"o":[[0,0],[0,0]],"v":[[528.909,637.787],[555.755,637.787]],"c":false},"ix":2},"nm":"Path 1","mn":"ADBE Vector Shape - Group","hd":false},{"ty":"st","c":{"a":0,"k":[0,0,0,1],"ix":3},"o":{"a":0,"k":100,"ix":4},"w":{"a":0,"k":5,"ix":5},"lc":1,"lj":1,"ml":10,"bm":0,"nm":"Stroke 1","mn":"ADBE Vector Graphic - Stroke","hd":false},{"ty":"tr","p":{"a":0,"k":[0,0],"ix":2},"a":{"a":0,"k":[0,0],"ix":1},"s":{"a":0,"k":[100,100],"ix":3},"r":{"a":0,"k":0,"ix":6},"o":{"a":0,"k":100,"ix":7},"sk":{"a":0,"k":0,"ix":4},"sa":{"a":0,"k":0,"ix":5},"nm":"Transform"}],"nm":"Group 1","np":2,"cix":2,"bm":0,"ix":1,"mn":"ADBE Vector Group","hd":false},{"ty":"gr","it":[{"ind":0,"ty":"sh","ix":1,"ks":{"a":0,"k":{"i":[[0,0],[0,0]],"o":[[0,0],[0,0]],"v":[[528.909,637.787],[555.755,637.787]],"c":true},"ix":2},"nm":"Path 1","mn":"ADBE Vector Shape - Group","hd":false},{"ty":"fl","c":{"a":0,"k":[1,1,1,1],"ix":4},"o":{"a":0,"k":100,"ix":5},"r":1,"bm":0,"nm":"Fill 1","mn":"ADBE Vector Graphic - Fill","hd":false},{"ty":"tr","p":{"a":0,"k":[0,0],"ix":2},"a":{"a":0,"k":[0,0],"ix":1},"s":{"a":0,"k":[100,100],"ix":3},"r":{"a":0,"k":0,"ix":6},"o":{"a":0,"k":100,"ix":7},"sk":{"a":0,"k":0,"ix":4},"sa":{"a":0,"k":0,"ix":5},"nm":"Transform"}],"nm":"Group 2","np":2,"cix":2,"bm":0,"ix":2,"mn":"ADBE Vector Group","hd":false},{"ty":"gr","it":[{"ind":0,"ty":"sh","ix":1,"ks":{"a":0,"k":{"i":[[0,0],[0,0]],"o":[[0,0],[0,0]],"v":[[528.909,621.925],[555.755,621.925]],"c":false},"ix":2},"nm":"Path 1","mn":"ADBE Vector Shape - Group","hd":false},{"ty":"st","c":{"a":0,"k":[0,0,0,1],"ix":3},"o":{"a":0,"k":100,"ix":4},"w":{"a":0,"k":5,"ix":5},"lc":1,"lj":1,"ml":10,"bm":0,"nm":"Stroke 1","mn":"ADBE Vector Graphic - Stroke","hd":false},{"ty":"tr","p":{"a":0,"k":[0,0],"ix":2},"a":{"a":0,"k":[0,0],"ix":1},"s":{"a":0,"k":[100,100],"ix":3},"r":{"a":0,"k":0,"ix":6},"o":{"a":0,"k":100,"ix":7},"sk":{"a":0,"k":0,"ix":4},"sa":{"a":0,"k":0,"ix":5},"nm":"Transform"}],"nm":"Group 3","np":2,"cix":2,"bm":0,"ix":3,"mn":"ADBE Vector Group","hd":false},{"ty":"gr","it":[{"ind":0,"ty":"sh","ix":1,"ks":{"a":0,"k":{"i":[[0,0],[0,0]],"o":[[0,0],[0,0]],"v":[[528.909,621.925],[555.755,621.925]],"c":true},"ix":2},"nm":"Path 1","mn":"ADBE Vector Shape - Group","hd":false},{"ty":"fl","c":{"a":0,"k":[1,1,1,1],"ix":4},"o":{"a":0,"k":100,"ix":5},"r":1,"bm":0,"nm":"Fill 1","mn":"ADBE Vector Graphic - Fill","hd":false},{"ty":"tr","p":{"a":0,"k":[0,0],"ix":2},"a":{"a":0,"k":[0,0],"ix":1},"s":{"a":0,"k":[100,100],"ix":3},"r":{"a":0,"k":0,"ix":6},"o":{"a":0,"k":100,"ix":7},"sk":{"a":0,"k":0,"ix":4},"sa":{"a":0,"k":0,"ix":5},"nm":"Transform"}],"nm":"Group 4","np":2,"cix":2,"bm":0,"ix":4,"mn":"ADBE Vector Group","hd":false},{"ty":"gr","it":[{"ind":0,"ty":"sh","ix":1,"ks":{"a":0,"k":{"i":[[0,0],[0,0]],"o":[[0,0],[0,0]],"v":[[528.909,606.741],[555.755,606.741]],"c":false},"ix":2},"nm":"Path 1","mn":"ADBE Vector Shape - Group","hd":false},{"ty":"st","c":{"a":0,"k":[0,0,0,1],"ix":3},"o":{"a":0,"k":100,"ix":4},"w":{"a":0,"k":5,"ix":5},"lc":1,"lj":1,"ml":10,"bm":0,"nm":"Stroke 1","mn":"ADBE Vector Graphic - Stroke","hd":false},{"ty":"tr","p":{"a":0,"k":[0,0],"ix":2},"a":{"a":0,"k":[0,0],"ix":1},"s":{"a":0,"k":[100,100],"ix":3},"r":{"a":0,"k":0,"ix":6},"o":{"a":0,"k":100,"ix":7},"sk":{"a":0,"k":0,"ix":4},"sa":{"a":0,"k":0,"ix":5},"nm":"Transform"}],"nm":"Group 5","np":2,"cix":2,"bm":0,"ix":5,"mn":"ADBE Vector Group","hd":false},{"ty":"gr","it":[{"ind":0,"ty":"sh","ix":1,"ks":{"a":0,"k":{"i":[[0,0],[0,0]],"o":[[0,0],[0,0]],"v":[[528.909,606.741],[555.755,606.741]],"c":true},"ix":2},"nm":"Path 1","mn":"ADBE Vector Shape - Group","hd":false},{"ty":"fl","c":{"a":0,"k":[1,1,1,1],"ix":4},"o":{"a":0,"k":100,"ix":5},"r":1,"bm":0,"nm":"Fill 1","mn":"ADBE Vector Graphic - Fill","hd":false},{"ty":"tr","p":{"a":0,"k":[0,0],"ix":2},"a":{"a":0,"k":[0,0],"ix":1},"s":{"a":0,"k":[100,100],"ix":3},"r":{"a":0,"k":0,"ix":6},"o":{"a":0,"k":100,"ix":7},"sk":{"a":0,"k":0,"ix":4},"sa":{"a":0,"k":0,"ix":5},"nm":"Transform"}],"nm":"Group 6","np":2,"cix":2,"bm":0,"ix":6,"mn":"ADBE Vector Group","hd":false},{"ty":"gr","it":[{"ind":0,"ty":"sh","ix":1,"ks":{"a":0,"k":{"i":[[0,0],[0,0]],"o":[[0,0],[0,0]],"v":[[528.909,591.879],[555.755,591.879]],"c":false},"ix":2},"nm":"Path 1","mn":"ADBE Vector Shape - Group","hd":false},{"ty":"st","c":{"a":0,"k":[0,0,0,1],"ix":3},"o":{"a":0,"k":100,"ix":4},"w":{"a":0,"k":5,"ix":5},"lc":1,"lj":1,"ml":10,"bm":0,"nm":"Stroke 1","mn":"ADBE Vector Graphic - Stroke","hd":false},{"ty":"tr","p":{"a":0,"k":[0,0],"ix":2},"a":{"a":0,"k":[0,0],"ix":1},"s":{"a":0,"k":[100,100],"ix":3},"r":{"a":0,"k":0,"ix":6},"o":{"a":0,"k":100,"ix":7},"sk":{"a":0,"k":0,"ix":4},"sa":{"a":0,"k":0,"ix":5},"nm":"Transform"}],"nm":"Group 7","np":2,"cix":2,"bm":0,"ix":7,"mn":"ADBE Vector Group","hd":false},{"ty":"gr","it":[{"ind":0,"ty":"sh","ix":1,"ks":{"a":0,"k":{"i":[[0,0],[0,0]],"o":[[0,0],[0,0]],"v":[[528.909,591.879],[555.755,591.879]],"c":true},"ix":2},"nm":"Path 1","mn":"ADBE Vector Shape - Group","hd":false},{"ty":"fl","c":{"a":0,"k":[1,1,1,1],"ix":4},"o":{"a":0,"k":100,"ix":5},"r":1,"bm":0,"nm":"Fill 1","mn":"ADBE Vector Graphic - Fill","hd":false},{"ty":"tr","p":{"a":0,"k":[0,0],"ix":2},"a":{"a":0,"k":[0,0],"ix":1},"s":{"a":0,"k":[100,100],"ix":3},"r":{"a":0,"k":0,"ix":6},"o":{"a":0,"k":100,"ix":7},"sk":{"a":0,"k":0,"ix":4},"sa":{"a":0,"k":0,"ix":5},"nm":"Transform"}],"nm":"Group 8","np":2,"cix":2,"bm":0,"ix":8,"mn":"ADBE Vector Group","hd":false},{"ty":"gr","it":[{"ind":0,"ty":"sh","ix":1,"ks":{"a":0,"k":{"i":[[0,0],[0,0]],"o":[[0,0],[0,0]],"v":[[528.909,560.039],[555.755,560.039]],"c":false},"ix":2},"nm":"Path 1","mn":"ADBE Vector Shape - Group","hd":false},{"ty":"st","c":{"a":0,"k":[0,0,0,1],"ix":3},"o":{"a":0,"k":100,"ix":4},"w":{"a":0,"k":5,"ix":5},"lc":1,"lj":1,"ml":10,"bm":0,"nm":"Stroke 1","mn":"ADBE Vector Graphic - Stroke","hd":false},{"ty":"tr","p":{"a":0,"k":[0,0],"ix":2},"a":{"a":0,"k":[0,0],"ix":1},"s":{"a":0,"k":[100,100],"ix":3},"r":{"a":0,"k":0,"ix":6},"o":{"a":0,"k":100,"ix":7},"sk":{"a":0,"k":0,"ix":4},"sa":{"a":0,"k":0,"ix":5},"nm":"Transform"}],"nm":"Group 9","np":2,"cix":2,"bm":0,"ix":9,"mn":"ADBE Vector Group","hd":false},{"ty":"gr","it":[{"ind":0,"ty":"sh","ix":1,"ks":{"a":0,"k":{"i":[[0,0],[0,0]],"o":[[0,0],[0,0]],"v":[[528.909,560.039],[555.755,560.039]],"c":true},"ix":2},"nm":"Path 1","mn":"ADBE Vector Shape - Group","hd":false},{"ty":"fl","c":{"a":0,"k":[1,1,1,1],"ix":4},"o":{"a":0,"k":100,"ix":5},"r":1,"bm":0,"nm":"Fill 1","mn":"ADBE Vector Graphic - Fill","hd":false},{"ty":"tr","p":{"a":0,"k":[0,0],"ix":2},"a":{"a":0,"k":[0,0],"ix":1},"s":{"a":0,"k":[100,100],"ix":3},"r":{"a":0,"k":0,"ix":6},"o":{"a":0,"k":100,"ix":7},"sk":{"a":0,"k":0,"ix":4},"sa":{"a":0,"k":0,"ix":5},"nm":"Transform"}],"nm":"Group 10","np":2,"cix":2,"bm":0,"ix":10,"mn":"ADBE Vector Group","hd":false},{"ty":"gr","it":[{"ind":0,"ty":"sh","ix":1,"ks":{"a":0,"k":{"i":[[0,0],[0,0]],"o":[[0,0],[0,0]],"v":[[528.909,545.176],[555.755,545.176]],"c":false},"ix":2},"nm":"Path 1","mn":"ADBE Vector Shape - Group","hd":false},{"ty":"st","c":{"a":0,"k":[0,0,0,1],"ix":3},"o":{"a":0,"k":100,"ix":4},"w":{"a":0,"k":5,"ix":5},"lc":1,"lj":1,"ml":10,"bm":0,"nm":"Stroke 1","mn":"ADBE Vector Graphic - Stroke","hd":false},{"ty":"tr","p":{"a":0,"k":[0,0],"ix":2},"a":{"a":0,"k":[0,0],"ix":1},"s":{"a":0,"k":[100,100],"ix":3},"r":{"a":0,"k":0,"ix":6},"o":{"a":0,"k":100,"ix":7},"sk":{"a":0,"k":0,"ix":4},"sa":{"a":0,"k":0,"ix":5},"nm":"Transform"}],"nm":"Group 11","np":2,"cix":2,"bm":0,"ix":11,"mn":"ADBE Vector Group","hd":false},{"ty":"gr","it":[{"ind":0,"ty":"sh","ix":1,"ks":{"a":0,"k":{"i":[[0,0],[0,0]],"o":[[0,0],[0,0]],"v":[[528.909,545.176],[555.755,545.176]],"c":true},"ix":2},"nm":"Path 1","mn":"ADBE Vector Shape - Group","hd":false},{"ty":"fl","c":{"a":0,"k":[1,1,1,1],"ix":4},"o":{"a":0,"k":100,"ix":5},"r":1,"bm":0,"nm":"Fill 1","mn":"ADBE Vector Graphic - Fill","hd":false},{"ty":"tr","p":{"a":0,"k":[0,0],"ix":2},"a":{"a":0,"k":[0,0],"ix":1},"s":{"a":0,"k":[100,100],"ix":3},"r":{"a":0,"k":0,"ix":6},"o":{"a":0,"k":100,"ix":7},"sk":{"a":0,"k":0,"ix":4},"sa":{"a":0,"k":0,"ix":5},"nm":"Transform"}],"nm":"Group 12","np":2,"cix":2,"bm":0,"ix":12,"mn":"ADBE Vector Group","hd":false},{"ty":"gr","it":[{"ind":0,"ty":"sh","ix":1,"ks":{"a":0,"k":{"i":[[0,0],[0,0]],"o":[[0,0],[0,0]],"v":[[528.909,528.993],[555.755,528.993]],"c":false},"ix":2},"nm":"Path 1","mn":"ADBE Vector Shape - Group","hd":false},{"ty":"st","c":{"a":0,"k":[0,0,0,1],"ix":3},"o":{"a":0,"k":100,"ix":4},"w":{"a":0,"k":5,"ix":5},"lc":1,"lj":1,"ml":10,"bm":0,"nm":"Stroke 1","mn":"ADBE Vector Graphic - Stroke","hd":false},{"ty":"tr","p":{"a":0,"k":[0,0],"ix":2},"a":{"a":0,"k":[0,0],"ix":1},"s":{"a":0,"k":[100,100],"ix":3},"r":{"a":0,"k":0,"ix":6},"o":{"a":0,"k":100,"ix":7},"sk":{"a":0,"k":0,"ix":4},"sa":{"a":0,"k":0,"ix":5},"nm":"Transform"}],"nm":"Group 13","np":2,"cix":2,"bm":0,"ix":13,"mn":"ADBE Vector Group","hd":false},{"ty":"gr","it":[{"ind":0,"ty":"sh","ix":1,"ks":{"a":0,"k":{"i":[[0,0],[0,0]],"o":[[0,0],[0,0]],"v":[[528.909,528.993],[555.755,528.993]],"c":true},"ix":2},"nm":"Path 1","mn":"ADBE Vector Shape - Group","hd":false},{"ty":"fl","c":{"a":0,"k":[1,1,1,1],"ix":4},"o":{"a":0,"k":100,"ix":5},"r":1,"bm":0,"nm":"Fill 1","mn":"ADBE Vector Graphic - Fill","hd":false},{"ty":"tr","p":{"a":0,"k":[0,0],"ix":2},"a":{"a":0,"k":[0,0],"ix":1},"s":{"a":0,"k":[100,100],"ix":3},"r":{"a":0,"k":0,"ix":6},"o":{"a":0,"k":100,"ix":7},"sk":{"a":0,"k":0,"ix":4},"sa":{"a":0,"k":0,"ix":5},"nm":"Transform"}],"nm":"Group 14","np":2,"cix":2,"bm":0,"ix":14,"mn":"ADBE Vector Group","hd":false},{"ty":"gr","it":[{"ind":0,"ty":"sh","ix":1,"ks":{"a":0,"k":{"i":[[0,0],[0,0]],"o":[[0,0],[0,0]],"v":[[528.909,514.13],[555.755,514.13]],"c":false},"ix":2},"nm":"Path 1","mn":"ADBE Vector Shape - Group","hd":false},{"ty":"st","c":{"a":0,"k":[0,0,0,1],"ix":3},"o":{"a":0,"k":100,"ix":4},"w":{"a":0,"k":5,"ix":5},"lc":1,"lj":1,"ml":10,"bm":0,"nm":"Stroke 1","mn":"ADBE Vector Graphic - Stroke","hd":false},{"ty":"tr","p":{"a":0,"k":[0,0],"ix":2},"a":{"a":0,"k":[0,0],"ix":1},"s":{"a":0,"k":[100,100],"ix":3},"r":{"a":0,"k":0,"ix":6},"o":{"a":0,"k":100,"ix":7},"sk":{"a":0,"k":0,"ix":4},"sa":{"a":0,"k":0,"ix":5},"nm":"Transform"}],"nm":"Group 15","np":2,"cix":2,"bm":0,"ix":15,"mn":"ADBE Vector Group","hd":false},{"ty":"gr","it":[{"ind":0,"ty":"sh","ix":1,"ks":{"a":0,"k":{"i":[[0,0],[0,0]],"o":[[0,0],[0,0]],"v":[[528.909,514.13],[555.755,514.13]],"c":true},"ix":2},"nm":"Path 1","mn":"ADBE Vector Shape - Group","hd":false},{"ty":"fl","c":{"a":0,"k":[1,1,1,1],"ix":4},"o":{"a":0,"k":100,"ix":5},"r":1,"bm":0,"nm":"Fill 1","mn":"ADBE Vector Graphic - Fill","hd":false},{"ty":"tr","p":{"a":0,"k":[0,0],"ix":2},"a":{"a":0,"k":[0,0],"ix":1},"s":{"a":0,"k":[100,100],"ix":3},"r":{"a":0,"k":0,"ix":6},"o":{"a":0,"k":100,"ix":7},"sk":{"a":0,"k":0,"ix":4},"sa":{"a":0,"k":0,"ix":5},"nm":"Transform"}],"nm":"Group 16","np":2,"cix":2,"bm":0,"ix":16,"mn":"ADBE Vector Group","hd":false},{"ty":"gr","it":[{"ind":0,"ty":"sh","ix":1,"ks":{"a":0,"k":{"i":[[0,0],[0,0]],"o":[[0,0],[0,0]],"v":[[528.909,653.444],[571.909,653.444]],"c":false},"ix":2},"nm":"Path 1","mn":"ADBE Vector Shape - Group","hd":false},{"ty":"st","c":{"a":0,"k":[0,0,0,1],"ix":3},"o":{"a":0,"k":100,"ix":4},"w":{"a":0,"k":5,"ix":5},"lc":1,"lj":1,"ml":10,"bm":0,"nm":"Stroke 1","mn":"ADBE Vector Graphic - Stroke","hd":false},{"ty":"tr","p":{"a":0,"k":[0,0],"ix":2},"a":{"a":0,"k":[0,0],"ix":1},"s":{"a":0,"k":[100,100],"ix":3},"r":{"a":0,"k":0,"ix":6},"o":{"a":0,"k":100,"ix":7},"sk":{"a":0,"k":0,"ix":4},"sa":{"a":0,"k":0,"ix":5},"nm":"Transform"}],"nm":"Group 17","np":2,"cix":2,"bm":0,"ix":17,"mn":"ADBE Vector Group","hd":false},{"ty":"gr","it":[{"ind":0,"ty":"sh","ix":1,"ks":{"a":0,"k":{"i":[[0,0],[0,0]],"o":[[0,0],[0,0]],"v":[[528.909,653.445],[571.909,653.445]],"c":true},"ix":2},"nm":"Path 1","mn":"ADBE Vector Shape - Group","hd":false},{"ty":"fl","c":{"a":0,"k":[1,1,1,1],"ix":4},"o":{"a":0,"k":100,"ix":5},"r":1,"bm":0,"nm":"Fill 1","mn":"ADBE Vector Graphic - Fill","hd":false},{"ty":"tr","p":{"a":0,"k":[0,0],"ix":2},"a":{"a":0,"k":[0,0],"ix":1},"s":{"a":0,"k":[100,100],"ix":3},"r":{"a":0,"k":0,"ix":6},"o":{"a":0,"k":100,"ix":7},"sk":{"a":0,"k":0,"ix":4},"sa":{"a":0,"k":0,"ix":5},"nm":"Transform"}],"nm":"Group 18","np":2,"cix":2,"bm":0,"ix":18,"mn":"ADBE Vector Group","hd":false},{"ty":"gr","it":[{"ind":0,"ty":"sh","ix":1,"ks":{"a":0,"k":{"i":[[0,0],[0,0]],"o":[[0,0],[0,0]],"v":[[528.909,576.222],[571.909,576.222]],"c":false},"ix":2},"nm":"Path 1","mn":"ADBE Vector Shape - Group","hd":false},{"ty":"st","c":{"a":0,"k":[0,0,0,1],"ix":3},"o":{"a":0,"k":100,"ix":4},"w":{"a":0,"k":5,"ix":5},"lc":1,"lj":1,"ml":10,"bm":0,"nm":"Stroke 1","mn":"ADBE Vector Graphic - Stroke","hd":false},{"ty":"tr","p":{"a":0,"k":[0,0],"ix":2},"a":{"a":0,"k":[0,0],"ix":1},"s":{"a":0,"k":[100,100],"ix":3},"r":{"a":0,"k":0,"ix":6},"o":{"a":0,"k":100,"ix":7},"sk":{"a":0,"k":0,"ix":4},"sa":{"a":0,"k":0,"ix":5},"nm":"Transform"}],"nm":"Group 19","np":2,"cix":2,"bm":0,"ix":19,"mn":"ADBE Vector Group","hd":false},{"ty":"gr","it":[{"ind":0,"ty":"sh","ix":1,"ks":{"a":0,"k":{"i":[[0,0],[0,0]],"o":[[0,0],[0,0]],"v":[[528.909,576.222],[571.909,576.222]],"c":true},"ix":2},"nm":"Path 1","mn":"ADBE Vector Shape - Group","hd":false},{"ty":"fl","c":{"a":0,"k":[1,1,1,1],"ix":4},"o":{"a":0,"k":100,"ix":5},"r":1,"bm":0,"nm":"Fill 1","mn":"ADBE Vector Graphic - Fill","hd":false},{"ty":"tr","p":{"a":0,"k":[0,0],"ix":2},"a":{"a":0,"k":[0,0],"ix":1},"s":{"a":0,"k":[100,100],"ix":3},"r":{"a":0,"k":0,"ix":6},"o":{"a":0,"k":100,"ix":7},"sk":{"a":0,"k":0,"ix":4},"sa":{"a":0,"k":0,"ix":5},"nm":"Transform"}],"nm":"Group 20","np":2,"cix":2,"bm":0,"ix":20,"mn":"ADBE Vector Group","hd":false},{"ty":"gr","it":[{"ind":0,"ty":"sh","ix":1,"ks":{"a":0,"k":{"i":[[0,0],[0,0]],"o":[[0,0],[0,0]],"v":[[528.909,499],[571.909,499]],"c":false},"ix":2},"nm":"Path 1","mn":"ADBE Vector Shape - Group","hd":false},{"ty":"st","c":{"a":0,"k":[0,0,0,1],"ix":3},"o":{"a":0,"k":100,"ix":4},"w":{"a":0,"k":5,"ix":5},"lc":1,"lj":1,"ml":10,"bm":0,"nm":"Stroke 1","mn":"ADBE Vector Graphic - Stroke","hd":false},{"ty":"tr","p":{"a":0,"k":[0,0],"ix":2},"a":{"a":0,"k":[0,0],"ix":1},"s":{"a":0,"k":[100,100],"ix":3},"r":{"a":0,"k":0,"ix":6},"o":{"a":0,"k":100,"ix":7},"sk":{"a":0,"k":0,"ix":4},"sa":{"a":0,"k":0,"ix":5},"nm":"Transform"}],"nm":"Group 21","np":2,"cix":2,"bm":0,"ix":21,"mn":"ADBE Vector Group","hd":false},{"ty":"gr","it":[{"ind":0,"ty":"sh","ix":1,"ks":{"a":0,"k":{"i":[[0,0],[0,0]],"o":[[0,0],[0,0]],"v":[[528.909,499],[571.909,499]],"c":true},"ix":2},"nm":"Path 1","mn":"ADBE Vector Shape - Group","hd":false},{"ty":"fl","c":{"a":0,"k":[1,1,1,1],"ix":4},"o":{"a":0,"k":100,"ix":5},"r":1,"bm":0,"nm":"Fill 1","mn":"ADBE Vector Graphic - Fill","hd":false},{"ty":"tr","p":{"a":0,"k":[0,0],"ix":2},"a":{"a":0,"k":[0,0],"ix":1},"s":{"a":0,"k":[100,100],"ix":3},"r":{"a":0,"k":0,"ix":6},"o":{"a":0,"k":100,"ix":7},"sk":{"a":0,"k":0,"ix":4},"sa":{"a":0,"k":0,"ix":5},"nm":"Transform"}],"nm":"Group 22","np":2,"cix":2,"bm":0,"ix":22,"mn":"ADBE Vector Group","hd":false}],"ip":0,"op":456.000018573261,"st":0,"bm":0},{"ddd":0,"ind":14,"ty":4,"nm":"100o Outlines","sr":1,"ks":{"o":{"a":0,"k":100,"ix":11},"r":{"a":0,"k":0,"ix":10},"p":{"a":0,"k":[989,346,0],"ix":2},"a":{"a":0,"k":[0,0,0],"ix":1},"s":{"a":0,"k":[100,100,100],"ix":6}},"ao":0,"shapes":[{"ty":"gr","it":[{"ind":0,"ty":"sh","ix":1,"ks":{"a":0,"k":{"i":[[0,0],[0,0],[1.764,-1.456],[1.504,-0.522],[0,0],[-2.106,2.087],[0,0],[0,0]],"o":[[0,0],[-0.656,1.942],[-1.764,1.456],[0,0],[2.857,-1],[0,0],[0,0],[0,0]],"v":[[-22.987,-29.999],[-27.662,-29.999],[-31.292,-24.901],[-36.194,-21.934],[-36.194,-16.391],[-28.749,-21.021],[-28.749,2],[-22.987,2]],"c":true},"ix":2},"nm":"1","mn":"ADBE Vector Shape - Group","hd":false},{"ty":"st","c":{"a":0,"k":[0.006431999861,0.015584000419,0.069608000213,1],"ix":3},"o":{"a":0,"k":100,"ix":4},"w":{"a":0,"k":0.01,"ix":5},"lc":1,"lj":1,"ml":4,"bm":0,"nm":"Stroke 1","mn":"ADBE Vector Graphic - Stroke","hd":false},{"ty":"fl","c":{"a":0,"k":[0,0,0,1],"ix":4},"o":{"a":0,"k":100,"ix":5},"r":1,"bm":0,"nm":"Fill 1","mn":"ADBE Vector Graphic - Fill","hd":false},{"ty":"tr","p":{"a":0,"k":[0,0],"ix":2},"a":{"a":0,"k":[0,0],"ix":1},"s":{"a":0,"k":[100,100],"ix":3},"r":{"a":0,"k":0,"ix":6},"o":{"a":0,"k":100,"ix":7},"sk":{"a":0,"k":0,"ix":4},"sa":{"a":0,"k":0,"ix":5},"nm":"Transform"}],"nm":"1","np":3,"cix":2,"bm":0,"ix":1,"mn":"ADBE Vector Group","hd":false},{"ty":"gr","it":[{"ind":0,"ty":"sh","ix":1,"ks":{"a":0,"k":{"i":[[1.627,-2.174],[0,-6],[-1.791,-2.384],[-2.926,0],[-1.627,2.174],[0,6.029],[1.955,2.609],[2.912,0]],"o":[[-1.969,2.638],[0,6.116],[1.791,2.384],[2.912,0],[1.969,-2.637],[0,-6.043],[-1.641,-2.203],[-2.912,0]],"v":[[-11.441,-26.738],[-14.394,-13.782],[-11.707,-1.032],[-4.632,2.543],[2.177,-0.717],[5.13,-13.717],[2.197,-26.695],[-4.632,-29.999]],"c":true},"ix":2},"nm":"0","mn":"ADBE Vector Shape - Group","hd":false},{"ind":1,"ty":"sh","ix":2,"ks":{"a":0,"k":{"i":[[-0.54,-0.471],[-0.356,-1.398],[0,-3.739],[0.396,-1.565],[0.547,-0.471],[0.697,0],[0.54,0.464],[0.355,1.399],[0,3.739],[-0.397,1.58],[-0.547,0.471],[-0.697,0]],"o":[[0.54,0.471],[0.355,1.399],[0,3.739],[-0.301,1.217],[-0.547,0.471],[-0.697,0],[-0.54,-0.464],[-0.356,-1.398],[0,-3.739],[0.301,-1.217],[0.547,-0.471],[0.697,0]],"v":[[-2.776,-24.227],[-1.433,-21.423],[-0.9,-13.717],[-1.494,-5.761],[-2.766,-3.228],[-4.632,-2.522],[-6.488,-3.217],[-7.831,-6.011],[-8.365,-13.717],[-7.77,-21.695],[-6.498,-24.227],[-4.632,-24.934]],"c":true},"ix":2},"nm":"0","mn":"ADBE Vector Shape - Group","hd":false},{"ty":"mm","mm":1,"nm":"Merge Paths 1","mn":"ADBE Vector Filter - Merge","hd":false},{"ty":"st","c":{"a":0,"k":[0.006431999861,0.015584000419,0.069608000213,1],"ix":3},"o":{"a":0,"k":100,"ix":4},"w":{"a":0,"k":0.01,"ix":5},"lc":1,"lj":1,"ml":4,"bm":0,"nm":"Stroke 1","mn":"ADBE Vector Graphic - Stroke","hd":false},{"ty":"fl","c":{"a":0,"k":[0,0,0,1],"ix":4},"o":{"a":0,"k":100,"ix":5},"r":1,"bm":0,"nm":"Fill 1","mn":"ADBE Vector Graphic - Fill","hd":false},{"ty":"tr","p":{"a":0,"k":[0,0],"ix":2},"a":{"a":0,"k":[0,0],"ix":1},"s":{"a":0,"k":[100,100],"ix":3},"r":{"a":0,"k":0,"ix":6},"o":{"a":0,"k":100,"ix":7},"sk":{"a":0,"k":0,"ix":4},"sa":{"a":0,"k":0,"ix":5},"nm":"Transform"}],"nm":"0","np":5,"cix":2,"bm":0,"ix":2,"mn":"ADBE Vector Group","hd":false},{"ty":"gr","it":[{"ind":0,"ty":"sh","ix":1,"ks":{"a":0,"k":{"i":[[1.627,-2.174],[0,-6],[-1.791,-2.384],[-2.926,0],[-1.627,2.174],[0,6.029],[1.955,2.609],[2.912,0]],"o":[[-1.969,2.638],[0,6.116],[1.791,2.384],[2.912,0],[1.969,-2.637],[0,-6.043],[-1.641,-2.203],[-2.912,0]],"v":[[11.918,-26.738],[8.965,-13.782],[11.651,-1.032],[18.726,2.543],[25.535,-0.717],[28.488,-13.717],[25.555,-26.695],[18.726,-29.999]],"c":true},"ix":2},"nm":"0","mn":"ADBE Vector Shape - Group","hd":false},{"ind":1,"ty":"sh","ix":2,"ks":{"a":0,"k":{"i":[[-0.54,-0.471],[-0.356,-1.398],[0,-3.739],[0.396,-1.565],[0.547,-0.471],[0.697,0],[0.54,0.464],[0.355,1.399],[0,3.739],[-0.397,1.58],[-0.547,0.471],[-0.697,0]],"o":[[0.54,0.471],[0.355,1.399],[0,3.739],[-0.301,1.217],[-0.547,0.471],[-0.697,0],[-0.54,-0.464],[-0.356,-1.398],[0,-3.739],[0.301,-1.217],[0.547,-0.471],[0.697,0]],"v":[[20.582,-24.227],[21.926,-21.423],[22.459,-13.717],[21.864,-5.761],[20.593,-3.228],[18.726,-2.522],[16.87,-3.217],[15.527,-6.011],[14.994,-13.717],[15.589,-21.695],[16.86,-24.227],[18.726,-24.934]],"c":true},"ix":2},"nm":"0","mn":"ADBE Vector Shape - Group","hd":false},{"ty":"mm","mm":1,"nm":"Merge Paths 1","mn":"ADBE Vector Filter - Merge","hd":false},{"ty":"st","c":{"a":0,"k":[0.006431999861,0.015584000419,0.069608000213,1],"ix":3},"o":{"a":0,"k":100,"ix":4},"w":{"a":0,"k":0.01,"ix":5},"lc":1,"lj":1,"ml":4,"bm":0,"nm":"Stroke 1","mn":"ADBE Vector Graphic - Stroke","hd":false},{"ty":"fl","c":{"a":0,"k":[0,0,0,1],"ix":4},"o":{"a":0,"k":100,"ix":5},"r":1,"bm":0,"nm":"Fill 1","mn":"ADBE Vector Graphic - Fill","hd":false},{"ty":"tr","p":{"a":0,"k":[0,0],"ix":2},"a":{"a":0,"k":[0,0],"ix":1},"s":{"a":0,"k":[100,100],"ix":3},"r":{"a":0,"k":0,"ix":6},"o":{"a":0,"k":100,"ix":7},"sk":{"a":0,"k":0,"ix":4},"sa":{"a":0,"k":0,"ix":5},"nm":"Transform"}],"nm":"0","np":5,"cix":2,"bm":0,"ix":3,"mn":"ADBE Vector Group","hd":false},{"ty":"gr","it":[{"ind":0,"ty":"sh","ix":1,"ks":{"a":0,"k":{"i":[[-0.55,-1.077],[-1.056,-0.558],[-1.164,0],[-1.24,1.339],[0,2.036],[1.227,1.322],[1.921,0],[1.008,-0.583],[0.55,-1.107],[0,-1.183]],"o":[[0.55,1.077],[1.056,0.558],[1.881,0],[1.239,-1.339],[0,-2.019],[-1.228,-1.322],[-1.243,0],[-1.008,0.583],[-0.55,1.107],[0,1.546]],"v":[[32.365,-15.81],[34.774,-13.357],[38.104,-12.521],[42.784,-14.53],[44.644,-19.593],[42.802,-24.605],[38.08,-26.588],[34.702,-25.714],[32.365,-23.179],[31.54,-19.745]],"c":true},"ix":2},"nm":"o","mn":"ADBE Vector Shape - Group","hd":false},{"ind":1,"ty":"sh","ix":2,"ks":{"a":0,"k":{"i":[[-0.598,0.71],[-0.877,0],[-0.594,-0.71],[0,-1.318],[0.594,-0.71],[0.877,0],[0.598,0.71],[0,1.335]],"o":[[0.598,-0.71],[0.877,0],[0.594,0.71],[0,1.352],[-0.594,0.71],[-0.877,0],[-0.598,-0.71],[0,-1.335]],"v":[[35.88,-22.622],[38.092,-23.686],[40.298,-22.622],[41.188,-19.58],[40.298,-16.488],[38.092,-15.423],[35.88,-16.488],[34.983,-19.555]],"c":true},"ix":2},"nm":"o","mn":"ADBE Vector Shape - Group","hd":false},{"ty":"mm","mm":1,"nm":"Merge Paths 1","mn":"ADBE Vector Filter - Merge","hd":false},{"ty":"st","c":{"a":0,"k":[0.006431999861,0.015584000419,0.069608000213,1],"ix":3},"o":{"a":0,"k":100,"ix":4},"w":{"a":0,"k":0.01,"ix":5},"lc":1,"lj":1,"ml":4,"bm":0,"nm":"Stroke 1","mn":"ADBE Vector Graphic - Stroke","hd":false},{"ty":"fl","c":{"a":0,"k":[0,0,0,1],"ix":4},"o":{"a":0,"k":100,"ix":5},"r":1,"bm":0,"nm":"Fill 1","mn":"ADBE Vector Graphic - Fill","hd":false},{"ty":"tr","p":{"a":0,"k":[0,0],"ix":2},"a":{"a":0,"k":[0,0],"ix":1},"s":{"a":0,"k":[100,100],"ix":3},"r":{"a":0,"k":0,"ix":6},"o":{"a":0,"k":100,"ix":7},"sk":{"a":0,"k":0,"ix":4},"sa":{"a":0,"k":0,"ix":5},"nm":"Transform"}],"nm":"o","np":5,"cix":2,"bm":0,"ix":4,"mn":"ADBE Vector Group","hd":false}],"ip":0,"op":456.000018573261,"st":0,"bm":0},{"ddd":0,"ind":15,"ty":4,"nm":"Layer 3/termometer Outlines","sr":1,"ks":{"o":{"a":0,"k":100,"ix":11},"r":{"a":0,"k":0,"ix":10},"p":{"a":0,"k":[977,442,0],"ix":2},"a":{"a":0,"k":[610,610,0],"ix":1},"s":{"a":0,"k":[100,100,100],"ix":6}},"ao":0,"shapes":[{"ty":"gr","it":[{"ind":0,"ty":"sh","ix":1,"ks":{"a":0,"k":{"i":[[13.022,5.628],[0,0],[0,0],[0,0],[0,-15.089],[-20.252,0],[0,20.252]],"o":[[0,0],[0,0],[0,0],[-13.022,5.628],[0,20.252],[20.252,0],[0,-15.089]],"v":[[14.532,-9.511],[13.532,-178.831],[-15.532,-178.831],[-14.532,-9.511],[-36.67,24.162],[0,60.831],[36.67,24.162]],"c":true},"ix":2},"nm":"Path 1","mn":"ADBE Vector Shape - Group","hd":false},{"ty":"fl","c":{"a":0,"k":[0.980116421569,0.03274564556,0.068794385125,1],"ix":4},"o":{"a":0,"k":100,"ix":5},"r":1,"bm":0,"nm":"Fill 1","mn":"ADBE Vector Graphic - Fill","hd":false},{"ty":"tr","p":{"a":0,"k":[498.516,676.687],"ix":2},"a":{"a":0,"k":[0,0],"ix":1},"s":{"a":0,"k":[100,100],"ix":3},"r":{"a":0,"k":0,"ix":6},"o":{"a":0,"k":100,"ix":7},"sk":{"a":0,"k":0,"ix":4},"sa":{"a":0,"k":0,"ix":5},"nm":"Transform"}],"nm":"Group 1","np":2,"cix":2,"bm":0,"ix":1,"mn":"ADBE Vector Group","hd":false},{"ty":"gr","it":[{"ind":0,"ty":"sh","ix":1,"ks":{"a":0,"k":{"i":[[13.156,7.479],[0,0],[12.404,0],[0,-12.404],[0,0],[0,-15.379],[-24.021,0],[0,24.023]],"o":[[0,0],[0,-12.404],[-12.403,0],[0,0],[-12.048,7.734],[0,24.023],[24.022,0],[0,-16.215]],"v":[[21.458,54.292],[21.458,-124.157],[-1.001,-146.616],[-23.459,-124.157],[-23.459,55.502],[-43.496,92.12],[-0.001,135.616],[43.495,92.12]],"c":true},"ix":2},"nm":"Path 1","mn":"ADBE Vector Shape - Group","hd":false},{"ty":"st","c":{"a":0,"k":[0,0,0,1],"ix":3},"o":{"a":0,"k":100,"ix":4},"w":{"a":0,"k":1,"ix":5},"lc":1,"lj":1,"ml":10,"bm":0,"nm":"Stroke 1","mn":"ADBE Vector Graphic - Stroke","hd":false},{"ty":"fl","c":{"a":0,"k":[1,1,1,1],"ix":4},"o":{"a":0,"k":100,"ix":5},"r":1,"bm":0,"nm":"Fill 1","mn":"ADBE Vector Graphic - Fill","hd":false},{"ty":"tr","p":{"a":0,"k":[498.516,609],"ix":2},"a":{"a":0,"k":[0,0],"ix":1},"s":{"a":0,"k":[100,100],"ix":3},"r":{"a":0,"k":0,"ix":6},"o":{"a":0,"k":100,"ix":7},"sk":{"a":0,"k":0,"ix":4},"sa":{"a":0,"k":0,"ix":5},"nm":"Transform"}],"nm":"Group 2","np":3,"cix":2,"bm":0,"ix":2,"mn":"ADBE Vector Group","hd":false}],"ip":0,"op":456.000018573261,"st":0,"bm":0},{"ddd":0,"ind":17,"ty":4,"nm":"smoke","parent":2,"sr":1,"ks":{"o":{"a":1,"k":[{"i":{"x":[0.833],"y":[0.833]},"o":{"x":[0.167],"y":[0.167]},"t":0,"s":[0]},{"i":{"x":[0.833],"y":[0.833]},"o":{"x":[0.167],"y":[0.167]},"t":11,"s":[14.362]},{"i":{"x":[0.833],"y":[0.833]},"o":{"x":[0.167],"y":[0.167]},"t":438,"s":[14]},{"t":455.00001853253,"s":[0]}],"ix":11},"r":{"a":0,"k":0,"ix":10},"p":{"a":0,"k":[0,0,0],"ix":2},"a":{"a":0,"k":[0,0,0],"ix":1},"s":{"a":0,"k":[100,100,100],"ix":6}},"ao":0,"shapes":[{"ty":"gr","it":[{"ind":0,"ty":"sh","ix":1,"ks":{"a":1,"k":[{"i":{"x":0.667,"y":1},"o":{"x":0.333,"y":0},"t":12,"s":[{"i":[[0,0],[-26,-66],[12,-62],[64,18],[-38,-46],[-14,-56],[0,0],[6.319,-10.834],[0,-1.813],[-0.119,-0.233],[-0.158,-0.184],[-0.924,-0.555],[-1.533,-0.651],[-8.716,-2.284],[-15.421,0],[-16,84],[2,54],[-56,4],[-14,98]],"o":[[0,0],[26,66],[-12,62],[-64,-18],[38,46],[14,56],[0,0],[-1.399,2.399],[0,0.221],[0.091,0.178],[0.439,0.511],[1.011,0.607],[4.818,2.045],[37.818,9.909],[22,0],[16,-84],[-2,-54],[56,-4],[14,-98]],"v":[[90,-602],[-24,-526],[146,-404],[-60,-440],[-140,-354],[10,-214],[-84,-110],[-107.746,-84.419],[-110,-78],[-109.82,-77.318],[-109.445,-76.775],[-107.389,-75.173],[-103.557,-73.284],[-82.78,-66.719],[36,-46],[118,-170],[50,-320],[232,-304],[324,-480]],"c":true}]},{"i":{"x":0.667,"y":1},"o":{"x":0.333,"y":0},"t":60,"s":[{"i":[[0,0],[-26,-66],[14,-140],[64,18],[-38,-46],[-2,-64],[0,0],[6.319,-10.834],[0,-1.813],[-0.119,-0.233],[-0.158,-0.184],[-0.924,-0.555],[-1.533,-0.651],[-8.716,-2.284],[-15.421,0],[-24.897,81.805],[1.895,54.004],[-56,4],[-9.536,98.535]],"o":[[0,0],[26,66],[-6.284,62.837],[-64,-18],[38,46],[1.803,57.695],[0,0],[-1.399,2.399],[0,0.221],[0.091,0.178],[0.439,0.511],[1.011,0.607],[4.818,2.045],[37.818,9.909],[22,0],[28,-92],[-4,-114],[56,-4],[12,-124]],"v":[[62,-664],[-86,-580],[162,-472],[-44,-458],[-140,-354],[48,-202],[-84,-110],[-107.746,-84.419],[-110,-78],[-109.82,-77.318],[-109.445,-76.775],[-107.389,-75.173],[-103.557,-73.284],[-82.78,-66.719],[36,-46],[140,-162],[74,-306],[248,-322],[360,-476]],"c":true}]},{"i":{"x":0.667,"y":1},"o":{"x":0.333,"y":0},"t":120,"s":[{"i":[[0,0],[-26,-66],[14,-140],[69.382,14.498],[-38,-46],[-2,-64],[0,0],[6.319,-10.834],[0,-1.813],[-0.119,-0.233],[-0.158,-0.184],[-0.924,-0.555],[-1.533,-0.651],[-8.716,-2.284],[-15.421,0],[8.509,85.086],[1.895,54.004],[-50.875,23.742],[-9.536,98.535]],"o":[[0,0],[26,66],[-6.284,62.837],[-134,-28],[38,46],[1.803,57.695],[0,0],[-1.399,2.399],[0,0.221],[0.091,0.178],[0.439,0.511],[1.011,0.607],[4.818,2.045],[37.818,9.909],[22,0],[-16,-160],[-4,-114],[60,-28],[12,-124]],"v":[[62,-664],[-108,-590],[132,-560],[-78,-530],[-240,-332],[64,-212],[-84,-110],[-107.746,-84.419],[-110,-78],[-109.82,-77.318],[-109.445,-76.775],[-107.389,-75.173],[-103.557,-73.284],[-82.78,-66.719],[36,-46],[140,-192],[-30,-390],[250,-400],[346,-544]],"c":true}]},{"i":{"x":0.667,"y":1},"o":{"x":0.333,"y":0},"t":181,"s":[{"i":[[0,0],[-26,-66],[14,-140],[69.382,14.498],[-38,-46],[-2,-64],[36,-92],[-19.363,-20.814],[0,-1.813],[-1.369,-0.32],[-1.744,-0.263],[-8.929,-0.833],[-12.3,-0.96],[-12.971,-1.908],[1.351,13.514],[8.509,85.086],[1.895,54.004],[-50.875,23.742],[-9.536,98.535]],"o":[[0,0],[26,66],[-6.284,62.837],[-134,-28],[38,46],[1.803,57.695],[-12.587,32.166],[4.288,4.609],[0,0.283],[1.046,0.245],[4.84,0.731],[9.772,0.912],[38.651,3.016],[198.195,29.154],[-10,-100],[-16,-160],[-4,-114],[60,-28],[12,-124]],"v":[[62,-664],[-108,-590],[132,-600],[-78,-530],[-240,-332],[72,-310],[-176,-186],[-116.962,-87.836],[-110,-78],[-107.897,-77.093],[-103.689,-76.329],[-82.562,-73.968],[-48.836,-71.142],[47.806,-63.154],[-2,-160],[224,-304],[-66,-422],[258,-450],[320,-636]],"c":true}]},{"i":{"x":0.667,"y":1},"o":{"x":0.333,"y":0},"t":245,"s":[{"i":[[0,0],[-26,-66],[14,-140],[69.382,14.498],[-48,-118],[-2,-64],[126,-134],[-56.19,-54.781],[0,-2.875],[-2.172,-0.085],[-2.74,0.048],[-13.542,0.939],[-17.542,1.863],[6.945,10.873],[-24,50],[8.509,85.086],[1.895,54.004],[-50.875,23.742],[-9.536,98.535]],"o":[[0,0],[26,66],[-6.284,62.837],[-134,-28],[22.482,55.268],[1.803,57.695],[-59.356,63.124],[22.67,22.102],[0,0.289],[1.66,0.065],[7.604,-0.135],[14.82,-1.028],[53.25,-5.657],[-47.806,-74.846],[43.489,-90.602],[-16,-160],[-4,-114],[60,-28],[12,-124]],"v":[[62,-664],[-108,-590],[128,-618],[-72,-594],[-264,-556],[142,-398],[-180,-320],[-93.967,-104.033],[-54,-64],[-50.65,-63.442],[-44.009,-63.418],[-11.415,-65.054],[38.274,-69.425],[141.806,-83.154],[-42,-234],[342,-398],[-48,-534],[266,-576],[312,-682]],"c":true}]},{"i":{"x":0.667,"y":1},"o":{"x":0.333,"y":0},"t":304,"s":[{"i":[[0,0],[-26,-66],[14,-140],[69.382,14.498],[-48,-118],[-32.595,-55.115],[50,-170],[-2.754,-78.426],[0,-2.875],[-6.354,-0.782],[-7.55,-0.753],[-28.904,-1.621],[-17.542,1.863],[-9.157,9.089],[-24,50],[8.509,85.086],[1.895,54.004],[-50.875,23.742],[-9.536,98.535]],"o":[[0,0],[26,66],[-6.284,62.837],[-134,-28],[22.482,55.268],[110,186],[-24.449,83.127],[1.967,56.033],[0,0.289],[4.856,0.598],[20.954,2.09],[31.631,1.774],[53.25,-5.657],[180.194,-178.846],[43.489,-90.602],[-16,-160],[-4,-114],[60,-28],[12,-124]],"v":[[62,-700],[-120,-674],[128,-654],[-84,-678],[-264,-592],[126,-528],[-198,-342],[0.033,-160.033],[-150,-80],[-139.976,-78.33],[-121.147,-76.275],[-41.654,-70.094],[38.274,-69.425],[141.806,-83.154],[-50,-290],[342,-434],[-60,-618],[266,-612],[312,-718]],"c":true}]},{"i":{"x":0.667,"y":1},"o":{"x":0.333,"y":0},"t":349,"s":[{"i":[[0,0],[-26,-66],[14,-140],[69.382,14.498],[-48,-118],[-32.595,-55.115],[50,-170],[5.967,-99.967],[-92,-204],[-12.569,-5.602],[-12.485,-2.516],[-31.288,2.146],[16.906,5.039],[-11.996,4.749],[-24,50],[8.509,85.086],[1.895,54.004],[-50.875,23.742],[-9.536,98.535]],"o":[[0,0],[26,66],[-6.284,62.837],[-134,-28],[22.482,55.268],[110,186],[-24.449,83.127],[-3.341,55.968],[4.164,9.233],[9.605,4.281],[34.653,6.982],[34.24,-2.349],[-156.273,-46.575],[492.194,-194.846],[43.489,-90.602],[-16,-160],[-4,-114],[60,-28],[12,-124]],"v":[[62,-700],[-120,-700],[128,-680],[-84,-704],[-264,-618],[76,-630],[-188,-446],[60.033,-240.033],[-150,-80],[-123.916,-57.92],[-90.341,-47.802],[17.961,-42.191],[56.273,-55.425],[25.806,-131.154],[-64,-434],[350,-508],[-60,-644],[266,-638],[312,-718]],"c":true}]},{"i":{"x":0.833,"y":0.833},"o":{"x":0.167,"y":0},"t":401,"s":[{"i":[[0,0],[-26,-66],[14,-140],[69.382,14.498],[-48,-118],[-32.595,-55.115],[50,-170],[5.967,-99.967],[-364,-80],[-47.803,-0.111],[-16.466,1.026],[-24.207,31.678],[113.727,15.425],[-11.873,5.049],[-24,50],[8.509,85.086],[1.895,54.004],[-50.875,23.742],[-9.536,98.535]],"o":[[0,0],[26,66],[-6.284,62.837],[-134,-28],[22.482,55.268],[110,186],[-24.449,83.127],[-3.341,55.968],[63.493,13.955],[32.069,0.074],[32.603,-2.031],[41.827,-54.736],[-177.245,-24.04],[632.194,-268.846],[43.489,-90.602],[-16,-160],[-4,-114],[60,-28],[12,-124]],"v":[[62,-700],[-120,-700],[128,-680],[-84,-704],[-264,-618],[76,-630],[-198,-486],[8.033,-408.033],[50,-210],[-134.003,-62.624],[-16.172,-60.757],[228.173,-183.264],[158.273,-281.425],[27.806,-349.154],[-52,-548],[354,-602],[-60,-644],[266,-638],[312,-718]],"c":true}]},{"t":447.000018206683,"s":[{"i":[[0,0],[-26,-66],[13.606,-124.62],[68.321,15.188],[-46.028,-103.803],[-28.928,-55.289],[40.141,-136.48],[6.037,-82.392],[-292.229,-64.584],[-38.401,-0.135],[-13.25,0.787],[-19.616,25.323],[91,12.255],[-11.251,3.603],[-22.308,40.141],[3.676,84.872],[1.916,54.003],[-51.886,19.849],[-10.416,98.429]],"o":[[0,0],[26,66],[-7.411,62.672],[-120.198,-26.028],[25.542,53.441],[91.071,160.367],[-19.628,66.736],[-2.958,45.406],[50.974,11.247],[25.764,0.095],[26.261,-1.529],[33.779,-43.823],[-141.347,-18.896],[514.999,-213.882],[39.252,-72.738],[-9.69,-145.015],[-3.606,-102.169],[59.211,-23.268],[12.394,-118.873]],"v":[[27.219,-749.765],[-141.373,-734.78],[131.549,-625.58],[-119.569,-721.034],[-279.852,-635.034],[22.685,-617.064],[-177.522,-547.862],[-16.796,-480.225],[18.452,-183.973],[-129.235,-65.521],[-34.563,-63.915],[162.009,-161.952],[106.647,-240.385],[6.001,-293.465],[-36.649,-585.018],[325.467,-652.821],[-78.612,-649.204],[259.296,-572.144],[314.366,-671.073]],"c":true}]}],"ix":2},"nm":"Path 1","mn":"ADBE Vector Shape - Group","hd":false},{"ty":"fl","c":{"a":0,"k":[0.403688318589,0.415255438113,0.419730392157,1],"ix":4},"o":{"a":0,"k":100,"ix":5},"r":1,"bm":0,"nm":"Fill 1","mn":"ADBE Vector Graphic - Fill","hd":false},{"ty":"tr","p":{"a":0,"k":[0,0],"ix":2},"a":{"a":0,"k":[0,0],"ix":1},"s":{"a":0,"k":[100,100],"ix":3},"r":{"a":0,"k":0,"ix":6},"o":{"a":0,"k":100,"ix":7},"sk":{"a":0,"k":0,"ix":4},"sa":{"a":0,"k":0,"ix":5},"nm":"Transform"}],"nm":"Shape 1","np":3,"cix":2,"bm":0,"ix":1,"mn":"ADBE Vector Group","hd":false}],"ip":0,"op":456.000018573261,"st":0,"bm":0},{"ddd":0,"ind":18,"ty":4,"nm":"hotwater","parent":2,"sr":1,"ks":{"o":{"a":0,"k":100,"ix":11},"r":{"a":0,"k":0,"ix":10},"p":{"a":0,"k":[0,0,0],"ix":2},"a":{"a":0,"k":[0,0,0],"ix":1},"s":{"a":0,"k":[100,100,100],"ix":6}},"ao":0,"shapes":[{"ty":"gr","it":[{"ind":0,"ty":"sh","ix":1,"ks":{"a":1,"k":[{"i":{"x":0.667,"y":1},"o":{"x":0.333,"y":0},"t":0,"s":[{"i":[[24,4],[22,-8],[26,20],[18,-18],[0,0],[0,0],[0,0],[0,0],[18,8],[12,18]],"o":[[-24,-4],[-22,8],[-26,-20],[-32.985,32.985],[0,0],[0,0],[0,0],[0,0],[-18,-8],[-12,-18]],"v":[[52,-100],[-14,-110],[-74,-104],[-170,-90],[-180,-68],[-76,-32],[92,-40],[184,-72],[160,-106],[106,-104]],"c":true}]},{"i":{"x":0.667,"y":1},"o":{"x":0.333,"y":0},"t":34,"s":[{"i":[[24,4],[30,-10],[26,20],[18,-18],[0,0],[0,0],[0,0],[0,0],[11.449,-16.029],[72,-6]],"o":[[-24,-4],[-22.208,7.403],[-26,-20],[-32.985,32.985],[0,0],[0,0],[0,0],[0,0],[-20,28],[-35.931,2.994]],"v":[[54,-90],[-20,-108],[-92,-96],[-178,-102],[-156,-48],[-76,-32],[92,-40],[184,-72],[174,-76],[122,-108]],"c":true}]},{"i":{"x":0.667,"y":1},"o":{"x":0.333,"y":0},"t":65,"s":[{"i":[[24,4],[44,-34],[34.662,28.662],[18,-18],[0,0],[0,0],[0,0],[0,0],[11.449,-16.029],[72,-6]],"o":[[-24,-4],[-16.568,12.803],[-34.662,-28.662],[-32.985,32.985],[0,0],[0,0],[0,0],[0,0],[-20,28],[-35.931,2.994]],"v":[[84,-76],[16,-104],[-60,-102],[-166,-80],[-156,-48],[-76,-32],[92,-40],[184,-72],[174,-76],[142,-108]],"c":true}]},{"i":{"x":0.667,"y":1},"o":{"x":0.333,"y":0},"t":97,"s":[{"i":[[24,4],[44,-26],[34.662,28.662],[88,26],[0,0],[0,0],[0,0],[0,0],[11.449,-16.029],[72,-6]],"o":[[-24,-4],[-18.026,10.652],[-34.662,-28.662],[-44.736,-13.217],[0,0],[0,0],[0,0],[0,0],[-20,28],[-35.931,2.994]],"v":[[108,-84],[38,-104],[-36,-104],[-160,-100],[-156,-48],[-76,-32],[92,-40],[184,-72],[132,-50],[160,-104]],"c":true}]},{"i":{"x":0.667,"y":1},"o":{"x":0.333,"y":0},"t":128,"s":[{"i":[[24,4],[40,-16],[38.568,23.141],[122,60],[0,0],[0,0],[0,0],[0,0],[11.449,-16.029],[72,-6]],"o":[[-24,-4],[-19.441,7.776],[-40,-24],[-41.859,-20.586],[0,0],[0,0],[0,0],[0,0],[-20,28],[-35.931,2.994]],"v":[[118,-80],[44,-108],[-14,-114],[-140,-116],[-184,-66],[-74,-30],[94,-38],[186,-70],[134,-48],[160,-106]],"c":true}]},{"i":{"x":0.667,"y":1},"o":{"x":0.333,"y":0},"t":157,"s":[{"i":[[24,4],[48,-38],[51.546,-47.864],[72.318,-34.032],[50,-80],[0,0],[0,0],[0,0],[11.449,-16.029],[72,-6]],"o":[[-24,-4],[-16.417,12.996],[-56,52],[-34,16],[0,0],[0,0],[0,0],[0,0],[-20,28],[-35.931,2.994]],"v":[[172,-110],[122,-66],[52,-114],[-56,-100],[-184,-66],[-74,-30],[94,-38],[94,-24],[134,-48],[152,-70]],"c":true}]},{"i":{"x":0.667,"y":1},"o":{"x":0.333,"y":0},"t":186,"s":[{"i":[[24,4],[48,-38],[51.546,-47.864],[82,-70],[140,-106],[0,0],[0,0],[0,0],[11.449,-16.029],[-62.408,36.404]],"o":[[-24,-4],[-16.417,12.996],[-56,52],[-28.579,24.397],[0,0],[0,0],[0,0],[0,0],[-20,28],[24,-14]],"v":[[158,-72],[172,-80],[112,-102],[-8,-90],[-154,-68],[-118,-30],[94,-38],[94,-24],[134,-48],[152,-70]],"c":true}]},{"i":{"x":0.667,"y":1},"o":{"x":0.333,"y":0},"t":211,"s":[{"i":[[-54.662,22.362],[-14,30],[58.528,-39.019],[76.237,76.237],[0,0],[80,-14],[13.018,16.393],[0,0],[11.449,-16.029],[-62.408,36.404]],"o":[[44,-18],[8.854,-18.974],[-18,12],[-52,-52],[0,0],[-20.62,3.609],[-54,-68],[0,0],[-20,28],[24,-14]],"v":[[140,-56],[130,-24],[140,-50],[166,-100],[44,-66],[-44,-116],[-98,-82],[-178,-68],[24,-64],[80,-36]],"c":true}]},{"i":{"x":0.667,"y":1},"o":{"x":0.333,"y":0},"t":240,"s":[{"i":[[-54.662,22.362],[-14,30],[58.528,-39.019],[38,50],[0,0],[44,-36],[19.489,7.643],[0,0],[11.449,-16.029],[-78,-12]],"o":[[44,-18],[8.854,-18.974],[-18,12],[-64.412,-84.753],[0,0],[-16.202,13.256],[-102,-40],[0,0],[-20,28],[27.462,4.225]],"v":[[110,-54],[132,-26],[144,-48],[160,-96],[58,-76],[-44,-110],[-92,-114],[-178,-62],[-62,-32],[84,-34]],"c":true}]},{"i":{"x":0.667,"y":1},"o":{"x":0.333,"y":0},"t":270,"s":[{"i":[[-54.662,22.362],[-14,30],[-70,-14],[23.537,58.224],[0,0],[124,-66],[19.257,8.208],[0,0],[11.449,-16.029],[-78,-12]],"o":[[44,-18],[8.855,-18.974],[21.213,4.243],[-38,-94],[0,0],[-18.479,9.836],[-122,-52],[0,0],[-20,28],[27.462,4.225]],"v":[[-10,-40],[20,-36],[66,-44],[176,-70],[82,-78],[-22,-100],[-70,-104],[-180,-74],[-62,-32],[-42,-36]],"c":true}]},{"i":{"x":0.667,"y":1},"o":{"x":0.333,"y":0},"t":301,"s":[{"i":[[-54.662,22.362],[-14,30],[-70,-14],[23.537,58.224],[0,0],[94,-60],[19.257,8.208],[0,0],[11.449,-16.029],[-78,-12]],"o":[[44,-18],[8.855,-18.974],[21.213,4.243],[-38,-94],[0,0],[-17.646,11.263],[-122,-52],[0,0],[-20,28],[27.462,4.225]],"v":[[-2,-32],[20,-36],[74,-36],[176,-70],[130,-68],[26,-90],[-22,-94],[-172,-66],[-62,-32],[-42,-36]],"c":true}]},{"i":{"x":0.667,"y":1},"o":{"x":0.333,"y":0},"t":325,"s":[{"i":[[-54.662,22.362],[-14,30],[-70,-14],[-15.735,8.742],[0,0],[82,-56],[3.812,20.584],[0,0],[11.449,-16.029],[-78,-12]],"o":[[44,-18],[8.855,-18.974],[21.213,4.243],[18,-10],[0,0],[-17.287,11.806],[-10,-54],[0,0],[-20,28],[27.462,4.225]],"v":[[-2,-32],[20,-36],[74,-36],[156,-46],[184,-86],[78,-96],[-4,-106],[-140,-68],[-62,-32],[-42,-36]],"c":true}]},{"i":{"x":0.667,"y":1},"o":{"x":0.333,"y":0},"t":350,"s":[{"i":[[-54.662,22.362],[-14,30],[-70,-14],[-15.735,8.742],[0,0],[82,-56],[13.908,15.646],[0,0],[150,-74],[-78,-12]],"o":[[44,-18],[8.855,-18.974],[21.213,4.243],[18,-10],[0,0],[-17.287,11.806],[-32,-36],[0,0],[-30.858,15.224],[27.462,4.225]],"v":[[-2,-32],[20,-36],[74,-36],[158,-46],[186,-86],[92,-82],[68,-104],[-80,-70],[-160,-92],[-42,-36]],"c":true}]},{"i":{"x":0.667,"y":1},"o":{"x":0.333,"y":0},"t":374,"s":[{"i":[[-54.662,22.362],[-14,30],[-70,-14],[-15.735,8.742],[0,0],[80,-80],[-2.96,20.723],[0,0],[129.169,-86.112],[6,-66]],"o":[[44,-18],[8.855,-18.974],[21.213,4.243],[18,-10],[0,0],[-14.802,14.802],[8,-56],[0,0],[-30,20],[-2.516,27.671]],"v":[[-2,-32],[20,-36],[74,-36],[158,-46],[186,-86],[110,-86],[86,-108],[-2,-76],[-106,-100],[-184,-86]],"c":true}]},{"i":{"x":0.833,"y":0.833},"o":{"x":0.167,"y":0},"t":403,"s":[{"i":[[-54.662,22.362],[-14,30],[-70,-14],[-15.735,8.742],[5.643,-39.504],[124.977,-48.837],[28.607,12.714],[0,0],[76,-30],[92,-76]],"o":[[44,-18],[8.855,-18.974],[21.213,4.243],[18,-10],[-5.643,39.504],[-19.498,7.619],[-36,-16],[0,0],[-33.537,13.238],[-21.421,17.696]],"v":[[-2,-32],[20,-36],[74,-36],[158,-46],[126,-26],[122,-84],[122,-106],[44,-76],[-42,-94],[-160,-82]],"c":true}]},{"i":{"x":0.667,"y":1},"o":{"x":0.167,"y":0.167},"t":430,"s":[{"i":[[-1.283,9.902],[10.429,4.213],[-4.855,9.072],[7.157,-9.405],[-22.16,-2.96],[40.169,-8.108],[9.194,4.086],[0,0],[36.642,-4.214],[67.495,-29.071]],"o":[[-2.144,-8.5],[-12.083,-0.67],[-10.825,-12.208],[-16.598,19.169],[63.649,8.501],[-6.595,1.331],[-11.571,-5.143],[0,0],[-22.994,-1.174],[-15.028,-6.527]],"v":[[0.644,-86.144],[-37.072,-94.216],[-60.432,-122.144],[-128.578,-109.858],[-145.649,-88.501],[-46.361,-56.713],[101.642,-63.213],[139.003,-75.286],[95.075,-104.143],[-13.495,-104.929]],"c":true}]},{"t":454.000018491799,"s":[{"i":[[24,4],[22,-8],[26,20],[18,-18],[0,0],[0,0],[0,0],[0,0],[18,8],[12,18]],"o":[[-24,-4],[-22,8],[-26,-20],[-32.985,32.985],[0,0],[0,0],[0,0],[0,0],[-18,-8],[-12,-18]],"v":[[52,-100],[-14,-110],[-74,-104],[-170,-90],[-180,-68],[-76,-32],[92,-40],[184,-72],[160,-106],[106,-104]],"c":true}]}],"ix":2},"nm":"Path 1","mn":"ADBE Vector Shape - Group","hd":false},{"ty":"fl","c":{"a":0,"k":[0.208241406609,0.628399718042,0.790946691176,1],"ix":4},"o":{"a":0,"k":100,"ix":5},"r":1,"bm":0,"nm":"Fill 1","mn":"ADBE Vector Graphic - Fill","hd":false},{"ty":"tr","p":{"a":0,"k":[0,0],"ix":2},"a":{"a":0,"k":[0,0],"ix":1},"s":{"a":0,"k":[100,100],"ix":3},"r":{"a":0,"k":0,"ix":6},"o":{"a":0,"k":100,"ix":7},"sk":{"a":0,"k":0,"ix":4},"sa":{"a":0,"k":0,"ix":5},"nm":"Transform"}],"nm":"Shape 1","np":3,"cix":2,"bm":0,"ix":1,"mn":"ADBE Vector Group","hd":false}],"ip":0,"op":456.000018573261,"st":0,"bm":0}],"markers":[]}